Verilog/components/branch_predictor.v

// Branch Predictor with BTB (Branch Target Buffer)
module branch_predictor #(
    parameter ADDR_WIDTH = 32,
    parameter BTB_SIZE = 16
) (
    input wire clk,
    input wire reset,
    input wire [ADDR_WIDTH-1:0] pc_fetch,
    output reg predict_taken,
    output reg [ADDR_WIDTH-1:0] predicted_target,
    output reg prediction_valid,
    input wire update_en,
    input wire [ADDR_WIDTH-1:0] pc_update,
    input wire [ADDR_WIDTH-1:0] target_update,
    input wire branch_taken
);

localparam [1:0] ST_NTAKEN = 2'b10,
                 WK_NTAKEN = 2'b11,
                 WK_TAKEN  = 2'b00,
                 ST_TAKEN  = 2'b01;

localparam INDEX_WIDTH = $clog2(BTB_SIZE);

reg [ADDR_WIDTH-1:0] btb_targets [0:BTB_SIZE-1];
reg [1:0]            btb_counters [0:BTB_SIZE-1]; // 2-bit saturating counters
reg [ADDR_WIDTH-INDEX_WIDTH-2-1:0] btb_tags [0:BTB_SIZE-1]; // PC tags for matching
reg btb_valid [0:BTB_SIZE-1];

// Index generation (use lower bits of PC, excluding byte offset)
wire [INDEX_WIDTH-1:0] fetch_index = pc_fetch[INDEX_WIDTH+1:2];
wire [INDEX_WIDTH-1:0] update_index = pc_update[INDEX_WIDTH+1:2];

// Tag generation (upper bits of PC)
wire [ADDR_WIDTH-INDEX_WIDTH-2-1:0] fetch_tag = pc_fetch[ADDR_WIDTH-1:INDEX_WIDTH+2];
wire [ADDR_WIDTH-INDEX_WIDTH-2-1:0] update_tag = pc_update[ADDR_WIDTH-1:INDEX_WIDTH+2];

// Prediction Logic
wire tag_match = btb_valid[fetch_index] && (btb_tags[fetch_index] == fetch_tag);
wire [1:0] counter_val = btb_counters[fetch_index];

always @(*) begin
    if (!reset) begin
        // During reset, output no prediction
        prediction_valid = 1'b0;
        predict_taken = 1'b0;
        predicted_target = 32'h0;
    end else begin
        prediction_valid = tag_match;
        predict_taken = tag_match && (counter_val[1] == 1'b0); // Taken if upper bit is 0
        predicted_target = btb_targets[fetch_index];
    end
end

integer i;
always @(posedge clk) begin
    if (!reset) begin
        // Initialize all entries as invalid with weakly taken
        for (i = 0; i < BTB_SIZE; i = i + 1) begin
            btb_valid[i] <= 1'b0;
            btb_counters[i] <= WK_TAKEN;
            btb_targets[i] <= 0;
            btb_tags[i] <= 0;
        end
    end else if (update_en) begin
        // Update the BTB entry
        btb_valid[update_index] <= 1'b1;
        btb_tags[update_index] <= update_tag;
        btb_targets[update_index] <= target_update;

        // Update 2-bit saturating counter
        case (btb_counters[update_index])
            ST_NTAKEN: btb_counters[update_index] <= branch_taken ? WK_NTAKEN : ST_NTAKEN;
            WK_NTAKEN: btb_counters[update_index] <= branch_taken ? WK_TAKEN  : ST_NTAKEN;
            WK_TAKEN:  btb_counters[update_index] <= branch_taken ? ST_TAKEN  : WK_NTAKEN;
            ST_TAKEN:  btb_counters[update_index] <= branch_taken ? ST_TAKEN  : WK_TAKEN;
        endcase
    end
end

endmodule

Verilog/test/tb_2bit_bp.v
`timescale 1ns/1ps

module tb_2bit_bp;

    reg clk, reset;
    reg [31:0] pc_fetch, pc_update, target_update;
    reg update_en, branch_taken;
    wire predict_taken, prediction_valid;
    wire [31:0] predicted_target;

    // Instantiate DUT
    branch_predictor #(
        .BTB_SIZE(16),  // Updated to match optimized module
        .ADDR_WIDTH(32)
    ) dut (
        .clk(clk),
        .reset(reset),
        .pc_fetch(pc_fetch),
        .predict_taken(predict_taken),
        .predicted_target(predicted_target),
        .prediction_valid(prediction_valid),
        .update_en(update_en),
        .pc_update(pc_update),
        .target_update(target_update),
        .branch_taken(branch_taken)
    );

    // Clock generation
    initial begin
        clk = 0;
        forever #5 clk = ~clk;
    end

    // Test stimulus
    initial begin
        $dumpfile("./Verilog/dumps/tb_2bit_bp.vcd");
        $dumpvars(0, tb_2bit_bp);

        $display("\n=== Branch Predictor with BTB Test ===\n");

        // Initialize
        reset = 0;
        pc_fetch = 0;
        pc_update = 0;
        target_update = 0;
        update_en = 0;
        branch_taken = 0;
        #10;
        reset = 1;
        #10;

        // Test 1: First branch at 0x100 - not in BTB yet
        $display("Test 1: Cold miss - Branch at 0x100 not in BTB");
        pc_fetch = 32'h0000_0100;
        #10;
        $display("  PC: 0x%h, Valid: %b, Predict Taken: %b",
                 pc_fetch, prediction_valid, predict_taken);
        if (!prediction_valid)
            $display("  PASS: Branch not in BTB (cold miss)\n");
        else
            $display("  FAIL: Should not be valid\n");

        // Test 2: Train branch at 0x100 -> 0x200 (taken)
        $display("Test 2: Train branch 0x100 -> 0x200 (taken)");
        pc_update = 32'h0000_0100;
        target_update = 32'h0000_0200;
        branch_taken = 1;
        update_en = 1;
        #10;
        update_en = 0;
        #10;

        // Test 3: Predict same branch - should be valid now
        $display("Test 3: Predict trained branch at 0x100");
        pc_fetch = 32'h0000_0100;
        #10;
        $display("  PC: 0x%h, Valid: %b, Predict: %b, Target: 0x%h",
                 pc_fetch, prediction_valid, predict_taken, predicted_target);
        if (prediction_valid && predicted_target == 32'h0000_0200)
            $display("  PASS: Branch found in BTB with correct target\n");
        else
            $display("  FAIL: Should be valid with target 0x200\n");

        // Test 4: Train same branch as taken again (strengthen)
        $display("Test 4: Strengthen prediction (taken again)");
        pc_update = 32'h0000_0100;
        target_update = 32'h0000_0200;
        branch_taken = 1;
        update_en = 1;
        #10;
        update_en = 0;
        #10;

        pc_fetch = 32'h0000_0100;
        #10;
        $display("  Predict Taken: %b (should be strongly taken now)\n", predict_taken);

        // Test 5: Branch not taken once (weaken)
        $display("Test 5: Weaken prediction (not taken once)");
        pc_update = 32'h0000_0100;
        branch_taken = 0;
        update_en = 1;
        #10;
        update_en = 0;
        #10;

        pc_fetch = 32'h0000_0100;
        #10;
        $display("  Predict Taken: %b (should still predict taken - weakly)\n", predict_taken);

        // Test 6: Train different branch at 0x104 -> 0x300
        $display("Test 6: Train different branch at 0x104 -> 0x300");
        pc_update = 32'h0000_0104;
        target_update = 32'h0000_0300;
        branch_taken = 1;
        update_en = 1;
        #10;
        update_en = 0;
        #10;

        pc_fetch = 32'h0000_0104;
        #10;
        $display("  PC: 0x%h, Valid: %b, Target: 0x%h",
                 pc_fetch, prediction_valid, predicted_target);
        if (prediction_valid && predicted_target == 32'h0000_0300)
            $display("  PASS: Second branch stored correctly\n");
        else
            $display("  FAIL: Should have target 0x300\n");

        // Test 7: Verify first branch still works
        $display("Test 7: Check first branch still in BTB");
        pc_fetch = 32'h0000_0100;
        #10;
        $display("  PC: 0x%h, Valid: %b, Target: 0x%h",
                 pc_fetch, prediction_valid, predicted_target);
        if (prediction_valid && predicted_target == 32'h0000_0200)
            $display("  PASS: First branch still valid\n");
        else
            $display("  FAIL: First branch corrupted\n");

        // Test 8: Train branch to not taken (flip prediction)
        $display("Test 8: Train branch at 0x100 as not taken twice");
        pc_update = 32'h0000_0100;
        branch_taken = 0;
        update_en = 1;
        #10;
        #10;  // Second not-taken update
        update_en = 0;
        #10;

        pc_fetch = 32'h0000_0100;
        #10;
        $display("  Predict Taken: %b (should be NOT taken now)\n", predict_taken);
        if (!predict_taken)
            $display("  PASS: Prediction flipped to not-taken\n");
        else
            $display("  FAIL: Should predict not-taken\n");

        $display("=== All Tests Complete ===\n");
        #50;
        $finish;
    end

    // Timeout watchdog
    initial begin
        #5000;
        $display("ERROR: Testbench timeout!");
        $finish;
    end

endmodule

Verilog/dumps/tb_2bit_bp.vcd
$date
	Sun Mar  8 00:30:05 2026
$end
$version
	Icarus Verilog
$end
$timescale
	1ps
$end
$scope module tb_2bit_bp $end
$var wire 1 ! prediction_valid $end
$var wire 32 " predicted_target [31:0] $end
$var wire 1 # predict_taken $end
$var reg 1 $ branch_taken $end
$var reg 1 % clk $end
$var reg 32 & pc_fetch [31:0] $end
$var reg 32 ' pc_update [31:0] $end
$var reg 1 ( reset $end
$var reg 32 ) target_update [31:0] $end
$var reg 1 * update_en $end
$scope module dut $end
$var wire 1 $ branch_taken $end
$var wire 1 % clk $end
$var wire 2 + counter_val [1:0] $end
$var wire 32 , pc_fetch [31:0] $end
$var wire 32 - pc_update [31:0] $end
$var wire 1 ( reset $end
$var wire 1 . tag_match $end
$var wire 32 / target_update [31:0] $end
$var wire 1 * update_en $end
$var wire 26 0 update_tag [25:0] $end
$var wire 4 1 update_index [3:0] $end
$var wire 26 2 fetch_tag [25:0] $end
$var wire 4 3 fetch_index [3:0] $end
$var parameter 32 4 ADDR_WIDTH $end
$var parameter 32 5 BTB_SIZE $end
$var parameter 32 6 INDEX_WIDTH $end
$var parameter 2 7 ST_NTAKEN $end
$var parameter 2 8 ST_TAKEN $end
$var parameter 2 9 WK_NTAKEN $end
$var parameter 2 : WK_TAKEN $end
$var reg 1 # predict_taken $end
$var reg 32 ; predicted_target [31:0] $end
$var reg 1 ! prediction_valid $end
$var integer 32 < i [31:0] $end
$upscope $end
$upscope $end
$enddefinitions $end
$comment Show the parameter values. $end
$dumpall
b0 :
b11 9
b1 8
b10 7
b100 6
b10000 5
b100000 4
$end
#0
$dumpvars
bx <
bx ;
b0 3
b0 2
b0 1
b0 0
b0 /
x.
b0 -
b0 ,
bx +
0*
b0 )
0(
b0 '
b0 &
0%
0$
x#
bx "
x!
$end
#5000
b0 "
b0 ;
0#
0!
0.
b0 +
b10000 <
1%
#10000
0%
1(
#15000
1%
#20000
b100 2
0%
b100000000 &
b100000000 ,
#25000
1%
#30000
b100 0
0%
1*
1$
b1000000000 )
b1000000000 /
b100000000 '
b100000000 -
#35000
b1000000000 "
b1000000000 ;
1#
1!
1.
b1 +
1%
#40000
0%
0*
#45000
1%
#50000
0%
#55000
1%
#60000
0%
1*
#65000
1%
#70000
0%
0*
#75000
1%
#80000
0%
#85000
1%
#90000
0%
1*
0$
#95000
b0 +
1%
#100000
0%
0*
#105000
1%
#110000
0%
#115000
1%
#120000
b1 1
0%
1*
1$
b1100000000 )
b1100000000 /
b100000100 '
b100000100 -
#125000
1%
#130000
0%
0*
#135000
1%
#140000
b1 +
b1100000000 "
b1100000000 ;
b1 3
0%
b100000100 &
b100000100 ,
#145000
1%
#150000
b0 +
b1000000000 "
b1000000000 ;
b0 3
0%
b100000000 &
b100000000 ,
#155000
1%
#160000
b0 1
0%
1*
0$
b100000000 '
b100000000 -
#165000
b1100000000 "
b1100000000 ;
0#
b11 +
1%
#170000
0%
#175000
b10 +
1%
#180000
0%
0*
