Verilog/peripherals/axi4_apb_bridge.v
module axi4_apb_bridge #(
    parameter ADDR_WIDTH   = 32,
    parameter DATA_WIDTH   = 32,
    parameter ID_WIDTH     = 4,
    parameter N_APB_SLAVES = 4
)(
    input  wire                        ACLK,
    input  wire                        ARESETn,

    // ============================================================
    // AXI4 WRITE ADDRESS CHANNEL
    // ============================================================
    input  wire [ADDR_WIDTH-1:0]       S_AXI_AWADDR,
    input  wire                        S_AXI_AWVALID,
    output reg                         S_AXI_AWREADY,
    input  wire [ID_WIDTH-1:0]         S_AXI_AWID,
    input  wire [7:0]                  S_AXI_AWLEN,
    input  wire [2:0]                  S_AXI_AWSIZE,

    // ============================================================
    // AXI4 WRITE DATA CHANNEL
    // ============================================================
    input  wire [DATA_WIDTH-1:0]       S_AXI_WDATA,
    input  wire                        S_AXI_WVALID,
    output reg                         S_AXI_WREADY,
    input  wire [(DATA_WIDTH/8)-1:0]   S_AXI_WSTRB,

    // ============================================================
    // AXI4 WRITE RESPONSE CHANNEL
    // ============================================================
    output reg  [1:0]                  S_AXI_BRESP,
    output reg                         S_AXI_BVALID,
    input  wire                        S_AXI_BREADY,
    output reg  [ID_WIDTH-1:0]         S_AXI_BID,

    // ============================================================
    // AXI4 READ ADDRESS CHANNEL
    // ============================================================
    input  wire [ADDR_WIDTH-1:0]       S_AXI_ARADDR,
    input  wire                        S_AXI_ARVALID,
    output reg                         S_AXI_ARREADY,
    input  wire [ID_WIDTH-1:0]         S_AXI_ARID,
    input  wire [7:0]                  S_AXI_ARLEN,
    input  wire [2:0]                  S_AXI_ARSIZE,

    // ============================================================
    // AXI4 READ DATA CHANNEL
    // ============================================================
    output reg  [DATA_WIDTH-1:0]       S_AXI_RDATA,
    output reg  [1:0]                  S_AXI_RRESP,
    output reg                         S_AXI_RVALID,
    input  wire                        S_AXI_RREADY,
    output reg  [ID_WIDTH-1:0]         S_AXI_RID,
    output reg                         S_AXI_RLAST,

    // ============================================================
    // APB MASTER INTERFACE
    // ============================================================
    output reg  [ADDR_WIDTH-1:0]       PADDR,
    output reg                         PWRITE,
    output reg                         PENABLE,
    output reg  [DATA_WIDTH-1:0]       PWDATA,
    input  wire [DATA_WIDTH-1:0]       PRDATA,
    input  wire                        PREADY,
    input  wire                        PSLVERR,
    output reg  [N_APB_SLAVES-1:0]     PSEL
);

////===============================================================
  //      MY CODE
////===============================================================
    localparam [1:0] AXI_RESP_OKAY   = 2'b00;
    localparam [1:0] AXI_RESP_SLVERR = 2'b10;

    localparam [3:0] IDLE           = 4'd0,
                     WR_AXI_SETUP   = 4'd1,
                     RD_AXI_SETUP   = 4'd2,
                     WR_APB_SETUP   = 4'd3,
                     RD_APB_SETUP   = 4'd4,
                     WR_APB_ENABLE  = 4'd5,
                     RD_APB_ENABLE  = 4'd6,
                     WR_RESP        = 4'd7,
                     RD_RESP        = 4'd8;

    reg [3:0] state, next_state;

    reg [ADDR_WIDTH-1:0]     awaddr_reg;
    reg [ID_WIDTH-1:0]       awid_reg;
    reg [DATA_WIDTH-1:0]     wdata_reg;
    reg                      write_error;

    reg [ADDR_WIDTH-1:0]     araddr_reg;
    reg [ID_WIDTH-1:0]       arid_reg;
    reg [DATA_WIDTH-1:0]     rdata_reg;
    reg                      read_error;

    // ============================================================
    // NEXT STATE LOGIC
    // ============================================================
    always @(*) begin
        case (state)
            IDLE:          next_state = (S_AXI_AWVALID && S_AXI_WVALID) ? WR_APB_SETUP :
                                        (S_AXI_ARVALID)                  ? RD_APB_SETUP :
                                                                           IDLE;
            WR_APB_SETUP:  next_state = WR_APB_ENABLE;
            RD_APB_SETUP:  next_state = RD_APB_ENABLE;
            WR_APB_ENABLE: next_state = (PREADY) ? WR_RESP : WR_APB_ENABLE;
            RD_APB_ENABLE: next_state = (PREADY) ? RD_RESP : RD_APB_ENABLE;
            WR_RESP:       next_state = (S_AXI_BREADY) ? IDLE : WR_RESP;
            RD_RESP:       next_state = (S_AXI_RREADY) ? IDLE : RD_RESP;
            default:       next_state = IDLE;
        endcase
    end

    // ============================================================
    // STATE / REGISTER SEQUENTIAL BLOCK
    // ============================================================
    always @(posedge ACLK or negedge ARESETn) begin
        if (!ARESETn) begin
            state        <= IDLE;
            awaddr_reg   <= {ADDR_WIDTH{1'b0}};
            awid_reg     <= {ID_WIDTH{1'b0}};
            wdata_reg    <= {DATA_WIDTH{1'b0}};
            write_error  <= 1'b0;
            araddr_reg   <= {ADDR_WIDTH{1'b0}};
            arid_reg     <= {ID_WIDTH{1'b0}};
            rdata_reg    <= {DATA_WIDTH{1'b0}};
            read_error   <= 1'b0;
        end
        else begin
            state <= next_state;

            case (state)
                IDLE: begin
                    if (S_AXI_AWVALID && S_AXI_WVALID) begin
                        awaddr_reg <= S_AXI_AWADDR;
                        awid_reg   <= S_AXI_AWID;
                        wdata_reg  <= S_AXI_WDATA;
                    end
                    else if (S_AXI_ARVALID) begin
                        araddr_reg <= S_AXI_ARADDR;
                        arid_reg   <= S_AXI_ARID;
                    end
                end

                RD_APB_ENABLE: begin
                    if (PREADY)
                        rdata_reg <= PRDATA;
                end
            endcase
        end
    end

    // ============================================================
    // OUTPUT LOGIC
    // ============================================================
    always @(*) begin
        S_AXI_AWREADY = 1'b0;
        S_AXI_WREADY  = 1'b0;
        S_AXI_ARREADY = 1'b0;

        S_AXI_BRESP   = AXI_RESP_OKAY;
        S_AXI_BVALID  = 1'b0;
        S_AXI_BID     = awid_reg;

        S_AXI_RDATA   = rdata_reg;
        S_AXI_RRESP   = AXI_RESP_OKAY;
        S_AXI_RVALID  = 1'b0;
        S_AXI_RID     = arid_reg;
        S_AXI_RLAST   = 1'b1;

        PADDR         = {ADDR_WIDTH{1'b0}};
        PWRITE        = 1'b0;
        PENABLE       = 1'b0;
        PWDATA        = {DATA_WIDTH{1'b0}};
        case (state)
            IDLE: begin
                if (S_AXI_AWVALID && S_AXI_WVALID) begin
                    S_AXI_WREADY  = 1'b1;
                    S_AXI_AWREADY = 1'b1;
                end
                else if (S_AXI_ARVALID) begin
                    S_AXI_ARREADY = 1'b1;
                end
            end

            WR_APB_SETUP: begin
                PADDR   = awaddr_reg;
                PWRITE  = 1'b1;
                PWDATA  = wdata_reg;
            end

            RD_APB_SETUP: begin
                PADDR   = araddr_reg;
                PWRITE  = 1'b0;
            end

            WR_APB_ENABLE: begin
                PADDR   = awaddr_reg;
                PWRITE  = 1'b1;
                PENABLE = 1'b1;
                PWDATA  = wdata_reg;
            end

            RD_APB_ENABLE: begin
                PADDR   = araddr_reg;
                PWRITE  = 1'b0;
                PENABLE = 1'b1;
            end

            WR_RESP: begin
                S_AXI_BVALID = 1'b1;
                S_AXI_BRESP  = (PSLVERR) ? AXI_RESP_SLVERR : AXI_RESP_OKAY;   //write error not used now but must be used later
            end

            RD_RESP: begin
                S_AXI_RVALID = 1'b1;
                S_AXI_RRESP  = (PSLVERR) ? AXI_RESP_SLVERR : AXI_RESP_OKAY;    //read error not used now but must be used later
            end
        endcase
    end

///===================================================================
///  PSEL COMBINATIONAL CODE
///===================================================================
always @(*) begin
    PSEL = 4'b0000;

    case (state)
        WR_APB_SETUP, WR_APB_ENABLE: begin
            if (awaddr_reg >= 32'h0000_2000 && awaddr_reg <= 32'h0000_203F)
                PSEL = 4'b0001;
            else if (awaddr_reg >= 32'h0000_2040 && awaddr_reg <= 32'h0000_207F)
                PSEL = 4'b0010;
            else if (awaddr_reg >= 32'h0000_2080 && awaddr_reg <= 32'h0000_20BF)
                PSEL = 4'b0100;
            else if (awaddr_reg >= 32'h0000_20C0 && awaddr_reg <= 32'h0000_20FF)
                PSEL = 4'b1000;
        end

        RD_APB_SETUP, RD_APB_ENABLE: begin
            if (araddr_reg >= 32'h0000_2000 && araddr_reg <= 32'h0000_203F)
                PSEL = 4'b0001;
            else if (araddr_reg >= 32'h0000_2040 && araddr_reg <= 32'h0000_207F)
                PSEL = 4'b0010;
            else if (araddr_reg >= 32'h0000_2080 && araddr_reg <= 32'h0000_20BF)
                PSEL = 4'b0100;
            else if (araddr_reg >= 32'h0000_20C0 && araddr_reg <= 32'h0000_20FF)
                PSEL = 4'b1000;
        end
    endcase
end
endmodule

Verilog/test/tb_axi4_apb_bridge.v
`timescale 1ns/1ps

module tb_axi4_apb_bridge;

    parameter ADDR_WIDTH = 32;
    parameter DATA_WIDTH = 32;
    parameter ID_WIDTH   = 4;

    reg ACLK;
    reg ARESETn;

    // AXI WRITE
    reg [ADDR_WIDTH-1:0] S_AXI_AWADDR;
    reg S_AXI_AWVALID;
    wire S_AXI_AWREADY;
    reg [ID_WIDTH-1:0] S_AXI_AWID;

    reg [DATA_WIDTH-1:0] S_AXI_WDATA;
    reg S_AXI_WVALID;
    wire S_AXI_WREADY;

    wire [1:0] S_AXI_BRESP;
    wire S_AXI_BVALID;
    reg S_AXI_BREADY;
    wire [ID_WIDTH-1:0] S_AXI_BID;

    // AXI READ
    reg [ADDR_WIDTH-1:0] S_AXI_ARADDR;
    reg S_AXI_ARVALID;
    wire S_AXI_ARREADY;
    reg [ID_WIDTH-1:0] S_AXI_ARID;

    wire [DATA_WIDTH-1:0] S_AXI_RDATA;
    wire [1:0] S_AXI_RRESP;
    wire S_AXI_RVALID;
    reg S_AXI_RREADY;
    wire [ID_WIDTH-1:0] S_AXI_RID;

    // APB
    wire [ADDR_WIDTH-1:0] PADDR;
    wire PWRITE;
    wire PENABLE;
    wire [DATA_WIDTH-1:0] PWDATA;
    reg  [DATA_WIDTH-1:0] PRDATA;
    reg  PREADY;
    reg  PSLVERR;
    wire [3:0] PSEL;

    // DUT
    axi4_apb_bridge dut (
        .ACLK(ACLK),
        .ARESETn(ARESETn),

        .S_AXI_AWADDR(S_AXI_AWADDR),
        .S_AXI_AWVALID(S_AXI_AWVALID),
        .S_AXI_AWREADY(S_AXI_AWREADY),
        .S_AXI_AWID(S_AXI_AWID),

        .S_AXI_WDATA(S_AXI_WDATA),
        .S_AXI_WVALID(S_AXI_WVALID),
        .S_AXI_WREADY(S_AXI_WREADY),

        .S_AXI_BRESP(S_AXI_BRESP),
        .S_AXI_BVALID(S_AXI_BVALID),
        .S_AXI_BREADY(S_AXI_BREADY),
        .S_AXI_BID(S_AXI_BID),

        .S_AXI_ARADDR(S_AXI_ARADDR),
        .S_AXI_ARVALID(S_AXI_ARVALID),
        .S_AXI_ARREADY(S_AXI_ARREADY),
        .S_AXI_ARID(S_AXI_ARID),

        .S_AXI_RDATA(S_AXI_RDATA),
        .S_AXI_RRESP(S_AXI_RRESP),
        .S_AXI_RVALID(S_AXI_RVALID),
        .S_AXI_RREADY(S_AXI_RREADY),
        .S_AXI_RID(S_AXI_RID),

        .PADDR(PADDR),
        .PWRITE(PWRITE),
        .PENABLE(PENABLE),
        .PWDATA(PWDATA),
        .PRDATA(PRDATA),
        .PREADY(PREADY),
        .PSLVERR(PSLVERR),
        .PSEL(PSEL)
    );

    // Clock
    always #5 ACLK = ~ACLK;

    // ============================================================
    // APB SLAVE MODEL (simple)
    // ============================================================
    always @(posedge ACLK) begin
        if (PENABLE) begin
            PREADY <= 1;
            if (!PWRITE) begin
                PRDATA <= 32'hABCD_1234; // fixed read data
            end
        end else begin
            PREADY <= 0;
        end
    end

    // ============================================================
    // TEST SEQUENCE
    // ============================================================
    initial begin
        $dumpfile("wave.vcd");
        $dumpvars(0, tb_axi4_apb_bridge);

        // init
        ACLK = 0;
        ARESETn = 0;

        S_AXI_AWVALID = 0;
        S_AXI_WVALID  = 0;
        S_AXI_BREADY  = 0;

        S_AXI_ARVALID = 0;
        S_AXI_RREADY  = 0;

        PREADY = 0;
        PSLVERR = 0;
        PRDATA = 0;

        #20;
        ARESETn = 1;

        // ========================================================
        // WRITE TRANSACTION
        // ========================================================
        @(posedge ACLK);
        S_AXI_AWADDR  = 32'h0000_2004;
        S_AXI_AWVALID = 1;
        S_AXI_WDATA   = 32'hDEADBEEF;
        S_AXI_WVALID  = 1;
        S_AXI_BREADY  = 1;

        wait (S_AXI_AWREADY && S_AXI_WREADY);
        @(posedge ACLK);
        S_AXI_AWVALID = 0;
        S_AXI_WVALID  = 0;

        wait (S_AXI_BVALID);
        $display("WRITE DONE: BRESP=%0d", S_AXI_BRESP);
        @(posedge ACLK);

        // ========================================================
        // READ TRANSACTION
        // ========================================================
        @(posedge ACLK);
        S_AXI_ARADDR  = 32'h0000_2004;
        S_AXI_ARVALID = 1;
        S_AXI_RREADY  = 1;

        wait (S_AXI_ARREADY);
        @(posedge ACLK);
        S_AXI_ARVALID = 0;

        wait (S_AXI_RVALID);
        $display("READ DONE: DATA=0x%h", S_AXI_RDATA);

        #20;
        $finish;
    end

    // ============================================================
    // DEBUG PRINTS
    // ============================================================
    always @(posedge ACLK) begin
        $display("T=%0t | PSEL=%b PADDR=%h PWRITE=%b PENABLE=%b PWDATA=%h",
                 $time, PSEL, PADDR, PWRITE, PENABLE, PWDATA);
    end

endmodule

Verilog/dumps/tb_axi_bridge.vcd
$date
	Sun Apr  5 22:51:17 2026
$end
$version
	Icarus Verilog
$end
$timescale
	1ps
$end
$scope module tb_axi4_apb_bridge $end
$var wire 1 ! S_AXI_WREADY $end
$var wire 1 " S_AXI_RVALID $end
$var wire 2 # S_AXI_RRESP [1:0] $end
$var wire 4 $ S_AXI_RID [3:0] $end
$var wire 32 % S_AXI_RDATA [31:0] $end
$var wire 1 & S_AXI_BVALID $end
$var wire 2 ' S_AXI_BRESP [1:0] $end
$var wire 4 ( S_AXI_BID [3:0] $end
$var wire 1 ) S_AXI_AWREADY $end
$var wire 1 * S_AXI_ARREADY $end
$var wire 1 + PWRITE $end
$var wire 32 , PWDATA [31:0] $end
$var wire 4 - PSEL [3:0] $end
$var wire 1 . PENABLE $end
$var wire 32 / PADDR [31:0] $end
$var parameter 32 0 ADDR_WIDTH $end
$var parameter 32 1 DATA_WIDTH $end
$var parameter 32 2 ID_WIDTH $end
$var reg 1 3 ACLK $end
$var reg 1 4 ARESETn $end
$var reg 32 5 PRDATA [31:0] $end
$var reg 1 6 PREADY $end
$var reg 1 7 PSLVERR $end
$var reg 32 8 S_AXI_ARADDR [31:0] $end
$var reg 4 9 S_AXI_ARID [3:0] $end
$var reg 1 : S_AXI_ARVALID $end
$var reg 32 ; S_AXI_AWADDR [31:0] $end
$var reg 4 < S_AXI_AWID [3:0] $end
$var reg 1 = S_AXI_AWVALID $end
$var reg 1 > S_AXI_BREADY $end
$var reg 1 ? S_AXI_RREADY $end
$var reg 32 @ S_AXI_WDATA [31:0] $end
$var reg 1 A S_AXI_WVALID $end
$scope module dut $end
$var wire 1 3 ACLK $end
$var wire 1 4 ARESETn $end
$var wire 32 B PRDATA [31:0] $end
$var wire 1 6 PREADY $end
$var wire 1 7 PSLVERR $end
$var wire 32 C S_AXI_ARADDR [31:0] $end
$var wire 4 D S_AXI_ARID [3:0] $end
$var wire 8 E S_AXI_ARLEN [7:0] $end
$var wire 3 F S_AXI_ARSIZE [2:0] $end
$var wire 1 : S_AXI_ARVALID $end
$var wire 32 G S_AXI_AWADDR [31:0] $end
$var wire 4 H S_AXI_AWID [3:0] $end
$var wire 8 I S_AXI_AWLEN [7:0] $end
$var wire 3 J S_AXI_AWSIZE [2:0] $end
$var wire 1 = S_AXI_AWVALID $end
$var wire 1 > S_AXI_BREADY $end
$var wire 1 ? S_AXI_RREADY $end
$var wire 32 K S_AXI_WDATA [31:0] $end
$var wire 4 L S_AXI_WSTRB [3:0] $end
$var wire 1 A S_AXI_WVALID $end
$var parameter 32 M ADDR_WIDTH $end
$var parameter 2 N AXI_RESP_OKAY $end
$var parameter 2 O AXI_RESP_SLVERR $end
$var parameter 32 P DATA_WIDTH $end
$var parameter 4 Q IDLE $end
$var parameter 32 R ID_WIDTH $end
$var parameter 32 S N_APB_SLAVES $end
$var parameter 4 T RD_APB_ENABLE $end
$var parameter 4 U RD_APB_SETUP $end
$var parameter 4 V RD_AXI_SETUP $end
$var parameter 4 W RD_RESP $end
$var parameter 4 X WR_APB_ENABLE $end
$var parameter 4 Y WR_APB_SETUP $end
$var parameter 4 Z WR_AXI_SETUP $end
$var parameter 4 [ WR_RESP $end
$var reg 32 \ PADDR [31:0] $end
$var reg 1 . PENABLE $end
$var reg 4 ] PSEL [3:0] $end
$var reg 32 ^ PWDATA [31:0] $end
$var reg 1 + PWRITE $end
$var reg 1 * S_AXI_ARREADY $end
$var reg 1 ) S_AXI_AWREADY $end
$var reg 4 _ S_AXI_BID [3:0] $end
$var reg 2 ` S_AXI_BRESP [1:0] $end
$var reg 1 & S_AXI_BVALID $end
$var reg 32 a S_AXI_RDATA [31:0] $end
$var reg 4 b S_AXI_RID [3:0] $end
$var reg 1 c S_AXI_RLAST $end
$var reg 2 d S_AXI_RRESP [1:0] $end
$var reg 1 " S_AXI_RVALID $end
$var reg 1 ! S_AXI_WREADY $end
$var reg 32 e araddr_reg [31:0] $end
$var reg 4 f arid_reg [3:0] $end
$var reg 32 g awaddr_reg [31:0] $end
$var reg 4 h awid_reg [3:0] $end
$var reg 4 i next_state [3:0] $end
$var reg 32 j rdata_reg [31:0] $end
$var reg 1 k read_error $end
$var reg 4 l state [3:0] $end
$var reg 32 m wdata_reg [31:0] $end
$var reg 1 n write_error $end
$upscope $end
$upscope $end
$enddefinitions $end
$comment Show the parameter values. $end
$dumpall
b111 [
b1 Z
b11 Y
b101 X
b1000 W
b10 V
b100 U
b110 T
b100 S
b100 R
b0 Q
b100000 P
b10 O
b0 N
b100000 M
b100 2
b100000 1
b100000 0
$end
#0
$dumpvars
0n
b0 m
b0 l
0k
b0 j
b0 i
b0 h
b0 g
b0 f
b0 e
b0 d
1c
b0 b
b0 a
b0 `
b0 _
b0 ^
b0 ]
b0 \
bz L
bx K
bz J
bz I
bx H
bx G
bz F
bz E
bx D
bx C
b0 B
0A
bx @
0?
0>
0=
bx <
bx ;
0:
bx 9
bx 8
07
06
b0 5
04
03
b0 /
0.
b0 -
b0 ,
0+
0*
0)
b0 (
b0 '
0&
b0 %
b0 $
b0 #
0"
0!
$end
#5000
13
#10000
03
#15000
13
#20000
03
14
#25000
bx (
bx _
b11011110101011011011111011101111 m
bx h
b10000000000100 g
1)
1!
b11 i
1>
1A
b11011110101011011011111011101111 @
b11011110101011011011111011101111 K
1=
b10000000000100 ;
b10000000000100 G
13
#30000
03
#35000
b1 -
b1 ]
b11011110101011011011111011101111 ,
b11011110101011011011111011101111 ^
1+
b10000000000100 /
b10000000000100 \
b11 l
0!
0)
b101 i
0A
0=
13
#40000
03
#45000
b1 -
b1 ]
1.
b11011110101011011011111011101111 ,
b11011110101011011011111011101111 ^
1+
b10000000000100 /
b10000000000100 \
b101 l
13
#50000
03
#55000
b111 i
16
13
#60000
03
#65000
b0 -
b0 ]
1&
b0 ,
b0 ^
0.
0+
b0 /
b0 \
b0 i
b111 l
13
#70000
03
#75000
0&
b0 l
06
13
#80000
03
#85000
bx $
bx b
bx f
b10000000000100 e
1*
b100 i
1?
1:
b10000000000100 8
b10000000000100 C
13
#90000
03
#95000
b1 -
b1 ]
b10000000000100 /
b10000000000100 \
b100 l
0*
b110 i
0:
13
#100000
03
#105000
b1 -
b1 ]
1.
b10000000000100 /
b10000000000100 \
b110 l
13
#110000
03
#115000
b1000 i
b10101011110011010001001000110100 5
b10101011110011010001001000110100 B
16
13
#120000
03
#125000
b0 -
b0 ]
1"
0.
b0 /
b0 \
b10101011110011010001001000110100 %
b10101011110011010001001000110100 a
b0 i
b10101011110011010001001000110100 j
b1000 l
13
#130000
03
#135000
0"
b0 l
06
13
