Verilog/components/csr_handler.v

module csr_handler (
    input         clk, reset, ivalid,

    input         csr_write_en,
    input  [11:0] csr_addr,
    input  [31:0] csr_write_data,
    output reg [31:0] csr_read_data
);

localparam  CSR_MSTATUS  = 12'h300,
            CSR_MISA     = 12'h301,
            CSR_MIE      = 12'h304,
            CSR_MTVEC    = 12'h305,
            CSR_MSTATUSH = 12'h310,
            CSR_MSCRATCH = 12'h340,
            CSR_MEPC     = 12'h341,
            CSR_MCAUSE   = 12'h342,
            CSR_MTVAL    = 12'h343,
            CSR_MIP      = 12'h344,
            CSR_MTINST   = 12'h345,
            CSR_MTVAL2   = 12'h346,
            CSR_MCYCLEL  = 12'hB00,
            CSR_INSTRETL = 12'hB02,
            CSR_MCYCLEH  = 12'hB80,
            CSR_INSTRETH = 12'hB82;

reg [63:0] cycle_counter, instret_counter;

// instruction retired counter
always @(posedge clk) begin
    if (!reset)
        instret_counter <= 64'b0;
    else if (ivalid)
        instret_counter <= instret_counter + 1'b1;
end
// cycle counter
always @(posedge clk) begin
    if (!reset)
        cycle_counter <= 64'b0;
    else
        cycle_counter <= cycle_counter + 1'b1;
end

always @(*) begin
    if (!reset) begin
        csr_read_data = 32'b0;
    end else begin
        case (csr_addr)
            CSR_MISA    : csr_read_data = {2'b01, 4'b000, 26'h0001100};
            CSR_MCYCLEH : csr_read_data = cycle_counter[63:32];
            CSR_MCYCLEL : csr_read_data = cycle_counter[31:0];
            CSR_INSTRETH: csr_read_data = instret_counter[63:32];
            CSR_INSTRETL: csr_read_data = instret_counter[31:0];
            default:      csr_read_data = 32'b0; // For unsupported CSRs, return 0
        endcase
    end
end

endmodule

Verilog/test/tb_csr_handler.v
`timescale 1ns / 1ps

module tb_csr_handler;


reg clk, reset, ivalid;
reg         csr_write_en;
reg  [11:0] csr_addr;
reg  [31:0] csr_write_data;

wire [31:0] csr_read_data;

csr_handler csr (
    clk, reset, ivalid, csr_write_en,
    csr_addr, csr_write_data, csr_read_data
);

// clock generation
always #7 clk = ~clk;

initial begin

    $dumpfile("./Verilog/dumps/tb_csr_handler.vcd");
    $dumpvars(0, tb_csr_handler);
    // Initialize
    clk = 0; reset = 0; ivalid = 0;
    csr_write_en = 0; csr_addr = 0; csr_write_data = 0;

    // reset
    # 28;
    reset = 1; #100;
    @(posedge clk);
    csr_addr = 12'h301; @(posedge clk); // misa
    @(posedge clk);
    csr_addr = 12'hB00; @(posedge clk); // mcyclel
    @(posedge clk);
    csr_addr = 12'hB80; @(posedge clk); // mcycleh
    @(posedge clk);
    repeat (5) @(posedge clk);
    csr_addr = 12'hB00; @(posedge clk); // mcyclel
    @(posedge clk);
    csr_addr = 12'hB80; @(posedge clk); // mcycleh
    @(posedge clk);
    $finish;
end

initial begin
    $monitor("time=%0t csr_addr=%h, csr_read_data=%h",
            $time, csr_addr, csr_read_data);
end

endmodule

Verilog/dumps/tb_csr_handler.vcd
$date
	Thu Mar 19 18:44:18 2026
$end
$version
	Icarus Verilog
$end
$timescale
	1ps
$end
$scope module tb_csr_handler $end
$var wire 32 ! csr_read_data [31:0] $end
$var reg 1 " clk $end
$var reg 12 # csr_addr [11:0] $end
$var reg 32 $ csr_write_data [31:0] $end
$var reg 1 % csr_write_en $end
$var reg 1 & ivalid $end
$var reg 1 ' reset $end
$scope module csr $end
$var wire 1 " clk $end
$var wire 12 ( csr_addr [11:0] $end
$var wire 32 ) csr_write_data [31:0] $end
$var wire 1 % csr_write_en $end
$var wire 1 & ivalid $end
$var wire 1 ' reset $end
$var parameter 12 * CSR_INSTRETH $end
$var parameter 12 + CSR_INSTRETL $end
$var parameter 12 , CSR_MCAUSE $end
$var parameter 12 - CSR_MCYCLEH $end
$var parameter 12 . CSR_MCYCLEL $end
$var parameter 12 / CSR_MEPC $end
$var parameter 12 0 CSR_MIE $end
$var parameter 12 1 CSR_MIP $end
$var parameter 12 2 CSR_MISA $end
$var parameter 12 3 CSR_MSCRATCH $end
$var parameter 12 4 CSR_MSTATUS $end
$var parameter 12 5 CSR_MSTATUSH $end
$var parameter 12 6 CSR_MTINST $end
$var parameter 12 7 CSR_MTVAL $end
$var parameter 12 8 CSR_MTVAL2 $end
$var parameter 12 9 CSR_MTVEC $end
$var reg 32 : csr_read_data [31:0] $end
$var reg 64 ; cycle_counter [63:0] $end
$var reg 64 < instret_counter [63:0] $end
$upscope $end
$upscope $end
$enddefinitions $end
$comment Show the parameter values. $end
$dumpall
b1100000101 9
b1101000110 8
b1101000011 7
b1101000101 6
b1100010000 5
b1100000000 4
b1101000000 3
b1100000001 2
b1101000100 1
b1100000100 0
b1101000001 /
b101100000000 .
b101110000000 -
b1101000010 ,
b101100000010 +
b101110000010 *
$end
#0
$dumpvars
bx <
bx ;
b0 :
b0 )
b0 (
0'
0&
0%
b0 $
b0 #
0"
b0 !
$end
#7000
b0 <
b0 ;
1"
#14000
0"
#21000
1"
#28000
0"
1'
#35000
b1 ;
1"
#42000
0"
#49000
b10 ;
1"
#56000
0"
#63000
b11 ;
1"
#70000
0"
#77000
b100 ;
1"
#84000
0"
#91000
b101 ;
1"
#98000
0"
#105000
b110 ;
1"
#112000
0"
#119000
b111 ;
1"
#126000
0"
#133000
b1000000000000000001000100000000 !
b1000000000000000001000100000000 :
b1000 ;
b1100000001 #
b1100000001 (
1"
#140000
0"
#147000
b1001 ;
1"
#154000
0"
#161000
b1010 !
b1010 :
b1010 ;
b101100000000 #
b101100000000 (
1"
#168000
0"
#175000
b1011 !
b1011 :
b1011 ;
1"
#182000
0"
#189000
b0 !
b0 :
b1100 ;
b101110000000 #
b101110000000 (
1"
#196000
0"
#203000
b1101 ;
1"
#210000
0"
#217000
b1110 ;
1"
#224000
0"
#231000
b1111 ;
1"
#238000
0"
#245000
b10000 ;
1"
#252000
0"
#259000
b10001 ;
1"
#266000
0"
#273000
b10010 ;
1"
#280000
0"
#287000
b10011 !
b10011 :
b10011 ;
b101100000000 #
b101100000000 (
1"
#294000
0"
#301000
b10100 !
b10100 :
b10100 ;
1"
#308000
0"
#315000
b0 !
b0 :
b10101 ;
b101110000000 #
b101110000000 (
1"
#322000
0"
#329000
b10110 ;
1"
#336000
0"
#343000
b10111 ;
1"
