Verilog/data_mem.v

// data_mem.v - word-accessible data memory
module data_mem #(parameter DATA_WIDTH = 32, ADDR_WIDTH = 32, MEM_SIZE = 2048) (
    input       clk,
    input [3:0] wea,
    input       [ADDR_WIDTH-1:0] addr,
    input       [DATA_WIDTH-1:0] wr_data,
    output reg  [DATA_WIDTH-1:0] rd_data
);

// array of 32-bit words
reg [DATA_WIDTH/4-1:0] data_ram0 [0:MEM_SIZE-1];
reg [DATA_WIDTH/4-1:0] data_ram1 [0:MEM_SIZE-1];
reg [DATA_WIDTH/4-1:0] data_ram2 [0:MEM_SIZE-1];
reg [DATA_WIDTH/4-1:0] data_ram3 [0:MEM_SIZE-1];

// word-aligned address
wire [ADDR_WIDTH-1:0] word_addr = addr[ADDR_WIDTH-1:2];

always @(posedge clk) begin
    rd_data <= {data_ram3[word_addr], data_ram2[word_addr], data_ram1[word_addr], data_ram0[word_addr]};
    if (|wea) begin  // write only if any byte enable is active
        if (wea[0]) data_ram0[word_addr] <= wr_data[7:0];
        if (wea[1]) data_ram1[word_addr] <= wr_data[15:8];
        if (wea[2]) data_ram2[word_addr] <= wr_data[23:16];
        if (wea[3]) data_ram3[word_addr] <= wr_data[31:24];
    end
end

endmodule

Verilog/test/tb_data_mem.v
`timescale 1ns/1ps

module tb_data_mem;

reg clk;
reg reset;
reg [3:0] wea;
reg [31:0] addr;
reg [31:0] wr_data;
wire [31:0] rd_data;

// Instantiate DUT
data_mem uut (
    .clk(clk), .wea(wea), .addr(addr),
    .wr_data(wr_data), .rd_data(rd_data)
);

// Clock generation
always #7 clk = ~clk;

// Task for writing
task write_mem;
input [31:0] address;
input [31:0] data;
input [3:0]  write_enable;
begin
    @(negedge clk);
    addr = address;
    wr_data = data;
    wea = write_enable;

    @(posedge clk);   // perform write

    @(negedge clk);
    wea = 4'b0000;    // disable write
end
endtask

// Task for reading
task read_mem;
input [31:0] address;
begin
    @(negedge clk);
    addr = address;

    @(posedge clk);   // synchronous read
    @(posedge clk);   // data available

    $display("Time=%0t | Address=%h | Read Data=%h", $time, address, rd_data);
end
endtask

initial begin
    $dumpfile("./Verilog/dumps/tb_data_mem.vcd");
    $dumpvars(0, tb_data_mem);
    // Initialize
    clk = 0; reset = 0; wea = 0; addr = 0; wr_data = 0;

    // Reset sequence
    #28;
    reset = 1; #100; // may be post-synthesis mem init delay?

    // TEST 1 : Full Word Write (SW)
    write_mem(32'h00000004, 32'hDEADBEEF, 4'b0011);
    read_mem(32'h00000004);

    // TEST 2 : Byte Write (SB)
    write_mem(32'h00000008, 32'h000000AA, 4'b0001);
    read_mem(32'h00000008);

    // TEST 3 : Half Word Write (SH)
    write_mem(32'h0000000C, 32'h0000BBBB, 4'b0011);
    read_mem(32'h0000000C);

    write_mem(32'h0000000F, 32'hAA00BBBB, 4'b1011);
    read_mem(32'h0000000F);

    write_mem(32'h00000004, 32'hAACCBBBB, 4'b1111);
    read_mem(32'h00000004);

    // TEST 4 : Read Different Address
    read_mem(32'h00000008);

    #50;
    $finish;

end

endmodule

Verilog/dumps/tb_data_mem.vcd
$date
	Thu Mar 26 15:40:24 2026
$end
$version
	Icarus Verilog
$end
$timescale
	1ps
$end
$scope module tb_data_mem $end
$var wire 32 ! rd_data [31:0] $end
$var reg 32 " addr [31:0] $end
$var reg 1 # clk $end
$var reg 1 $ reset $end
$var reg 4 % wea [3:0] $end
$var reg 32 & wr_data [31:0] $end
$scope module uut $end
$var wire 32 ' addr [31:0] $end
$var wire 1 # clk $end
$var wire 4 ( wea [3:0] $end
$var wire 32 ) wr_data [31:0] $end
$var wire 32 * word_addr [31:0] $end
$var parameter 32 + ADDR_WIDTH $end
$var parameter 32 , DATA_WIDTH $end
$var parameter 32 - MEM_SIZE $end
$var reg 32 . rd_data [31:0] $end
$upscope $end
$scope task read_mem $end
$var reg 32 / address [31:0] $end
$upscope $end
$scope task write_mem $end
$var reg 32 0 address [31:0] $end
$var reg 32 1 data [31:0] $end
$var reg 4 2 write_enable [3:0] $end
$upscope $end
$upscope $end
$enddefinitions $end
$comment Show the parameter values. $end
$dumpall
b100000000000 -
b100000 ,
b100000 +
$end
#0
$dumpvars
bx 2
bx 1
bx 0
bx /
bx .
b0 *
b0 )
b0 (
b0 '
b0 &
b0 %
0$
0#
b0 "
bx !
$end
#7000
1#
#14000
0#
#21000
1#
#28000
b1 *
b11 %
b11 (
b11011110101011011011111011101111 &
b11011110101011011011111011101111 )
b100 "
b100 '
0#
b11 2
b11011110101011011011111011101111 1
b100 0
1$
#35000
1#
#42000
b100 /
b0 %
b0 (
0#
#49000
bx1011111011101111 !
bx1011111011101111 .
1#
#56000
0#
#63000
1#
#70000
0#
#77000
b1 2
b10101010 1
b1000 0
1#
#84000
b10 *
b1 %
b1 (
b10101010 &
b10101010 )
b1000 "
b1000 '
0#
#91000
bx !
bx .
1#
#98000
b1000 /
b0 %
b0 (
0#
#105000
bx10101010 !
bx10101010 .
1#
#112000
0#
#119000
1#
#126000
0#
#133000
b11 2
b1011101110111011 1
b1100 0
1#
#140000
b11 *
b11 %
b11 (
b1011101110111011 &
b1011101110111011 )
b1100 "
b1100 '
0#
#147000
bx !
bx .
1#
#154000
b1100 /
b0 %
b0 (
0#
#161000
bx1011101110111011 !
bx1011101110111011 .
1#
#168000
0#
#175000
1#
#182000
0#
#189000
b1011 2
b10101010000000001011101110111011 1
b1111 0
1#
#196000
b1011 %
b1011 (
b10101010000000001011101110111011 &
b10101010000000001011101110111011 )
b1111 "
b1111 '
0#
#203000
1#
#210000
b1111 /
b0 %
b0 (
0#
#217000
b10101010xxxxxxxx1011101110111011 !
b10101010xxxxxxxx1011101110111011 .
1#
#224000
0#
#231000
1#
#238000
0#
#245000
b1111 2
b10101010110011001011101110111011 1
b100 0
1#
#252000
b1 *
b1111 %
b1111 (
b10101010110011001011101110111011 &
b10101010110011001011101110111011 )
b100 "
b100 '
0#
#259000
bx1011111011101111 !
bx1011111011101111 .
1#
#266000
b100 /
b0 %
b0 (
0#
#273000
b10101010110011001011101110111011 !
b10101010110011001011101110111011 .
1#
#280000
0#
#287000
1#
#294000
0#
#301000
b1000 /
1#
#308000
b10 *
b1000 "
b1000 '
0#
#315000
bx10101010 !
bx10101010 .
1#
