Verilog/peripherals/gpio.v
// gpio.v - GPIO peripheral for RISC-V SoC
// 32-bit bidirectional GPIO with direction control and interrupts
// Registers:
// GDIR - GPIO Direction Register         addr BASE + 0x00  (1=output, 0=input per bit)
// GDAT - GPIO Data Register              addr BASE + 0x04  (write: drive output, read: pin state)
// GIEN - GPIO Interrupt Enable Register  addr BASE + 0x08  (1=interrupt enabled for pin)
// GIRQ - GPIO Interrupt Flag Register    addr BASE + 0x0C  (read-to-clear, 1=edge detected)

module gpio #(
    parameter BASE_ADDR = 32'h0000_20C0
) (
    input  wire        clk,
    input  wire        resetn,

    // APB Interface
    input  wire        pclk,
    input  wire        presetn,
    input  wire        psel,
    input  wire        penable,
    input  wire        pwrite,
    input  wire [31:0] paddr,
    input  wire [31:0] pwdata,
    output reg  [31:0] prdata,
    output wire        pready,
    output reg         pslverr,

    // Interrupt
    output reg         irq,

    // GPIO pads (split for synthesis)
    input  wire [31:0] gpio_in,
    output wire [31:0] gpio_out,
    output wire [31:0] gpio_oe
);

localparam GDIR_ADDR = BASE_ADDR;           // BASE + 0x00
localparam GDAT_ADDR = BASE_ADDR + 32'h4;   // BASE + 0x04
localparam GIEN_ADDR = BASE_ADDR + 32'h8;   // BASE + 0x08
localparam GIRQ_ADDR = BASE_ADDR + 32'hC;   // BASE + 0x0C

reg [31:0] GDIR; // direction: 1=output
reg [31:0] GDAT; // output data
reg [31:0] GIEN; // interrupt enable: 1=enabled
reg [31:0] GIRQ; // interrupt flags (read-to-clear)
reg [31:0] gpio_in_prev; // previous input state for edge detection

// Combinational edge detection
wire [31:0] gpio_edge = gpio_in ^ gpio_in_prev;
wire [31:0] enabled_edges = gpio_edge & GIEN & ~GDIR;

// Drive signals — IOBUFs instantiated in soc_top
assign gpio_out = GDAT;
assign gpio_oe  = GDIR;

always @(posedge clk) begin // apb write
    if (!resetn) begin
        GDIR <= 32'b0; GDAT <= 32'b0; GIEN <= 32'b0; pslverr <= 1'b0;
    end else if (psel && penable && pwrite) begin
        pslverr <= 1'b0; // clear error by default
        case (paddr)
            GDIR_ADDR: GDIR <= pwdata;
            GDAT_ADDR: GDAT <= pwdata & GDIR; // only update output bits
            GIEN_ADDR: GIEN <= pwdata;        // interrupt enable
            default:   pslverr <= 1'b1;
        endcase
    end
end

always @(*) begin // apb read
    if (psel && penable && !pwrite) begin
        case (paddr)
            GDIR_ADDR: prdata = GDIR;
            GDAT_ADDR: prdata = gpio_in;  // read pin state, not output register
            GIEN_ADDR: prdata = GIEN;
            GIRQ_ADDR: prdata = GIRQ;     // read returns current flags
            default:   prdata = 32'b0;
        endcase
    end else begin
        prdata = 32'b0;
    end
end

assign pready = (psel && penable) ? 1'b1 : 1'b0;

// GIRQ management and IRQ generation
always @(posedge clk) begin
    if (!resetn) begin
        GIRQ <= 32'b0;
        gpio_in_prev <= 32'b0;
        irq <= 1'b0;
    end else begin
        // Update previous state for next cycle
        gpio_in_prev <= gpio_in;

        // Generate single-cycle IRQ pulse
        irq <= |enabled_edges;

        // Clear GIRQ when read
        if (psel && penable && !pwrite && paddr == GIRQ_ADDR) begin
            GIRQ <= 32'b0;
        end else begin
            // Accumulate edge events
            GIRQ <= GIRQ | enabled_edges;
        end
    end
end

endmodule

Verilog/test/tb_gpio.v
`timescale 1ns / 1ps
// Testbench for gpio.v — exercises APB write/read, tristate behaviour, and interrupts
// Register map (BASE = 0x0000_20C0):
//   GDIR  0x0000_20C0  direction register        (1=output, 0=input)
//   GDAT  0x0000_20C4  data register             (write: drive output; read: pin state)
//   GIEN  0x0000_20C8  interrupt enable register (1=interrupt enabled for pin)
//   GIRQ  0x0000_20CC  interrupt flag register   (read-to-clear, 1=edge detected)

module tb_gpio;

// DUT signals
reg         clk, resetn;
reg         psel, penable, pwrite;
reg  [31:0] paddr, pwdata;
wire [31:0] prdata;
wire        pready, pslverr, irq;

// Split GPIO ports (gpio.v now uses in/out/oe instead of inout)
wire [31:0] gpio_in_w, gpio_out_w, gpio_oe_w;

// Simulated bidirectional pad — models IOBUF tristate behaviour in TB
wire [31:0] gpio_pad;

// TB-side tristate drive onto gpio_pad
reg  [31:0] gpio_drive;
reg  [31:0] gpio_drive_en;

genvar i;
generate
    for (i = 0; i < 32; i = i + 1) begin : GPIO_PAD_MODEL
        // TB drives pad when gpio_drive_en[i]=1
        assign gpio_pad[i] = gpio_drive_en[i] ? gpio_drive[i] : 1'bz;
        // DUT drives pad when gpio_oe_w[i]=1 (output direction)
        assign gpio_pad[i] = gpio_oe_w[i] ? gpio_out_w[i] : 1'bz;
    end
endgenerate
// Pad value feeds back into DUT's input port
assign gpio_in_w = gpio_pad;

// DUT instantiation
gpio dut (
    .clk(clk),       .resetn(resetn),
    .pclk(clk),      .presetn(resetn),
    .psel(psel),     .penable(penable), .pwrite(pwrite),
    .paddr(paddr),   .pwdata(pwdata),
    .prdata(prdata), .pready(pready),   .pslverr(pslverr),
    .irq(irq),
    .gpio_in(gpio_in_w), .gpio_out(gpio_out_w), .gpio_oe(gpio_oe_w)
);

always #10 clk = ~clk; // 50 MHz

// ---- APB tasks (matching tb_timer.v style) ----

task apb_write(input [31:0] addr, input [31:0] data);
    begin
        @(posedge clk); #1;
        psel=1; pwrite=1; penable=0; paddr=addr; pwdata=data;
        @(posedge clk); #1;
        penable=1;
        @(posedge clk); #1;
        psel=0; penable=0; pwrite=0;
    end
endtask

task apb_read(input [31:0] addr);
    begin
        @(posedge clk); #1;
        psel=1; pwrite=0; penable=0; paddr=addr;
        @(posedge clk); #1;
        penable=1;
        @(posedge clk);
        $display("APB READ [%h] = %h", addr, prdata); #1;
        psel=0; penable=0;
    end
endtask

// ---- Test sequence ----

initial begin
    $dumpfile("./Verilog/dumps/tb_gpio.vcd");
    $dumpvars(0, tb_gpio);

    // Init
    clk=0; resetn=0;
    psel=0; penable=0; pwrite=0; paddr=0; pwdata=0;
    gpio_drive=0; gpio_drive_en=32'h0;
    #40;
    resetn=1;

    // =========================================================
    // TEST 1: OUTPUT MODE — DUT drives all 32 pins
    // =========================================================
    $display("\n===== TEST 1: OUTPUT MODE =====");
    apb_write(32'h0000_20C0, 32'hFFFF_FFFF); // GDIR = all outputs
    apb_write(32'h0000_20C4, 32'hA5A5_A5A5); // GDAT = pattern
    #20;
    $display("gpio_pad (expect A5A5A5A5) = %h", gpio_pad);

    // =========================================================
    // TEST 2: INPUT MODE — TB drives all 32 pins, DUT reads back
    // =========================================================
    $display("\n===== TEST 2: INPUT MODE =====");
    apb_write(32'h0000_20C0, 32'h0000_0000); // GDIR = all inputs
    gpio_drive_en = 32'hFFFF_FFFF;
    gpio_drive    = 32'h3C3C_3C3C;
    #20;
    apb_read(32'h0000_20C4); // expect 3C3C3C3C

    // =========================================================
    // TEST 3: MIXED MODE — upper 16 output (DUT), lower 16 input (TB)
    // =========================================================
    $display("\n===== TEST 3: MIXED MODE =====");
    apb_write(32'h0000_20C0, 32'hFFFF_0000); // upper=output, lower=input
    gpio_drive_en = 32'h0000_FFFF;           // TB drives lower 16
    gpio_drive    = 32'h0000_5555;
    apb_write(32'h0000_20C4, 32'hAAAA_0000); // DUT drives upper 16
    #20;
    apb_read(32'h0000_20C4); // expect AAAA5555

    // =========================================================
    // TEST 4: GDIR readback
    // =========================================================
    $display("\n===== TEST 4: GDIR READBACK =====");
    apb_write(32'h0000_20C0, 32'hDEAD_BEEF); // write GDIR
    apb_read(32'h0000_20C0);                  // expect DEADBEEF

    // =========================================================
    // TEST 5: CONTENTION — DUT and TB both drive opposite values
    // =========================================================
    $display("\n===== TEST 5: CONTENTION =====");
    apb_write(32'h0000_20C0, 32'hFFFF_FFFF); // DUT drives all
    gpio_drive_en = 32'hFFFF_FFFF;
    gpio_drive    = 32'h0000_0000;            // TB drives opposite
    #20;
    $display("gpio_pad (expect X on contended bits) = %h", gpio_pad);

    // =========================================================
    // TEST 6: pslverr on bad address
    // =========================================================
    $display("\n===== TEST 6: PSLVERR ON BAD ADDR =====");
    gpio_drive_en = 32'h0;                    // release TB drive
    apb_write(32'h0000_20D0, 32'h1234_5678); // invalid address (beyond GIRQ)
    #20;
    $display("pslverr after bad write = %b (expect 1)", pslverr);

    // =========================================================
    // TEST 7: GPIO INTERRUPT - single pin edge detection
    // =========================================================
    $display("\n===== TEST 7: GPIO INTERRUPT - SINGLE PIN =====");
    apb_write(32'h0000_20C0, 32'h0000_0000); // GDIR = all inputs
    apb_write(32'h0000_20C8, 32'h0000_0001); // GIEN = enable interrupt on GPIO[0]
    gpio_drive_en = 32'h0000_0001;
    gpio_drive    = 32'h0000_0000;
    #20;
    gpio_drive    = 32'h0000_0001;            // rising edge on GPIO[0]
    @(posedge clk); #2;                       // wait for clock edge + small delay
    $display("irq after edge (expect 1) = %b", irq);  // IRQ pulses this cycle
    @(posedge clk); #2;                       // next clock - IRQ goes back to 0
    $display("irq next cycle (expect 0) = %b", irq);
    apb_read(32'h0000_20CC);                  // read GIRQ (should see bit 0 set)
    #20;
    $display("irq after GIRQ read (expect 0) = %b", irq);

    // =========================================================
    // TEST 8: GPIO INTERRUPT - multiple pins
    // =========================================================
    $display("\n===== TEST 8: GPIO INTERRUPT - MULTIPLE PINS =====");
    apb_write(32'h0000_20C8, 32'h0000_00FF); // GIEN = enable interrupt on GPIO[7:0]
    gpio_drive_en = 32'h0000_00FF;
    gpio_drive    = 32'h0000_0000;
    #20;
    gpio_drive    = 32'h0000_00A5;            // toggle multiple pins
    @(posedge clk); #2;                       // wait for clock edge + small delay
    $display("irq after edges (expect 1) = %b", irq);  // IRQ pulses this cycle
    apb_read(32'h0000_20CC);                  // read GIRQ (should see 0xA5)
    @(posedge clk); #2;
    $display("irq after GIRQ read (expect 0) = %b", irq);

    // =========================================================
    // TEST 9: GPIO INTERRUPT - output pins should not generate IRQ
    // =========================================================
    $display("\n===== TEST 9: NO IRQ ON OUTPUT PINS =====");
    apb_write(32'h0000_20C0, 32'hFFFF_FFFF); // GDIR = all outputs
    apb_write(32'h0000_20C8, 32'hFFFF_FFFF); // GIEN = all enabled (but outputs shouldn't trigger)
    apb_write(32'h0000_20C4, 32'h0000_0000); // GDAT = all low
    #20;
    apb_write(32'h0000_20C4, 32'hFFFF_FFFF); // GDAT = all high (change output)
    #40;
    $display("irq after output change (expect 0) = %b", irq);
    apb_read(32'h0000_20CC);                  // read GIRQ (should be 0)

    #50;
    $display("\n===== ALL TESTS DONE =====");
    $finish;
end

endmodule

Verilog/dumps/tb_gpio.vcd
$date
	Fri Apr 24 01:12:30 2026
$end
$version
	Icarus Verilog
$end
$timescale
	1ps
$end
$scope module tb_gpio $end
$var wire 32 ! gpio_in_w [31:0] $end
$var wire 32 " gpio_pad [31:0] $end
$var wire 1 # pslverr $end
$var wire 1 $ pready $end
$var wire 32 % prdata [31:0] $end
$var wire 1 & irq $end
$var wire 32 ' gpio_out_w [31:0] $end
$var wire 32 ( gpio_oe_w [31:0] $end
$var reg 1 ) clk $end
$var reg 32 * gpio_drive [31:0] $end
$var reg 32 + gpio_drive_en [31:0] $end
$var reg 32 , paddr [31:0] $end
$var reg 1 - penable $end
$var reg 1 . psel $end
$var reg 32 / pwdata [31:0] $end
$var reg 1 0 pwrite $end
$var reg 1 1 resetn $end
$scope begin GPIO_PAD_MODEL[0] $end
$var parameter 2 2 i $end
$upscope $end
$scope begin GPIO_PAD_MODEL[1] $end
$var parameter 2 3 i $end
$upscope $end
$scope begin GPIO_PAD_MODEL[2] $end
$var parameter 3 4 i $end
$upscope $end
$scope begin GPIO_PAD_MODEL[3] $end
$var parameter 3 5 i $end
$upscope $end
$scope begin GPIO_PAD_MODEL[4] $end
$var parameter 4 6 i $end
$upscope $end
$scope begin GPIO_PAD_MODEL[5] $end
$var parameter 4 7 i $end
$upscope $end
$scope begin GPIO_PAD_MODEL[6] $end
$var parameter 4 8 i $end
$upscope $end
$scope begin GPIO_PAD_MODEL[7] $end
$var parameter 4 9 i $end
$upscope $end
$scope begin GPIO_PAD_MODEL[8] $end
$var parameter 5 : i $end
$upscope $end
$scope begin GPIO_PAD_MODEL[9] $end
$var parameter 5 ; i $end
$upscope $end
$scope begin GPIO_PAD_MODEL[10] $end
$var parameter 5 < i $end
$upscope $end
$scope begin GPIO_PAD_MODEL[11] $end
$var parameter 5 = i $end
$upscope $end
$scope begin GPIO_PAD_MODEL[12] $end
$var parameter 5 > i $end
$upscope $end
$scope begin GPIO_PAD_MODEL[13] $end
$var parameter 5 ? i $end
$upscope $end
$scope begin GPIO_PAD_MODEL[14] $end
$var parameter 5 @ i $end
$upscope $end
$scope begin GPIO_PAD_MODEL[15] $end
$var parameter 5 A i $end
$upscope $end
$scope begin GPIO_PAD_MODEL[16] $end
$var parameter 6 B i $end
$upscope $end
$scope begin GPIO_PAD_MODEL[17] $end
$var parameter 6 C i $end
$upscope $end
$scope begin GPIO_PAD_MODEL[18] $end
$var parameter 6 D i $end
$upscope $end
$scope begin GPIO_PAD_MODEL[19] $end
$var parameter 6 E i $end
$upscope $end
$scope begin GPIO_PAD_MODEL[20] $end
$var parameter 6 F i $end
$upscope $end
$scope begin GPIO_PAD_MODEL[21] $end
$var parameter 6 G i $end
$upscope $end
$scope begin GPIO_PAD_MODEL[22] $end
$var parameter 6 H i $end
$upscope $end
$scope begin GPIO_PAD_MODEL[23] $end
$var parameter 6 I i $end
$upscope $end
$scope begin GPIO_PAD_MODEL[24] $end
$var parameter 6 J i $end
$upscope $end
$scope begin GPIO_PAD_MODEL[25] $end
$var parameter 6 K i $end
$upscope $end
$scope begin GPIO_PAD_MODEL[26] $end
$var parameter 6 L i $end
$upscope $end
$scope begin GPIO_PAD_MODEL[27] $end
$var parameter 6 M i $end
$upscope $end
$scope begin GPIO_PAD_MODEL[28] $end
$var parameter 6 N i $end
$upscope $end
$scope begin GPIO_PAD_MODEL[29] $end
$var parameter 6 O i $end
$upscope $end
$scope begin GPIO_PAD_MODEL[30] $end
$var parameter 6 P i $end
$upscope $end
$scope begin GPIO_PAD_MODEL[31] $end
$var parameter 6 Q i $end
$upscope $end
$scope module dut $end
$var wire 1 ) clk $end
$var wire 32 R enabled_edges [31:0] $end
$var wire 32 S gpio_edge [31:0] $end
$var wire 32 T gpio_in [31:0] $end
$var wire 32 U gpio_oe [31:0] $end
$var wire 32 V gpio_out [31:0] $end
$var wire 32 W paddr [31:0] $end
$var wire 1 ) pclk $end
$var wire 1 - penable $end
$var wire 1 1 presetn $end
$var wire 1 . psel $end
$var wire 32 X pwdata [31:0] $end
$var wire 1 0 pwrite $end
$var wire 1 1 resetn $end
$var wire 1 $ pready $end
$var parameter 32 Y BASE_ADDR $end
$var parameter 33 Z GDAT_ADDR $end
$var parameter 32 [ GDIR_ADDR $end
$var parameter 33 \ GIEN_ADDR $end
$var parameter 33 ] GIRQ_ADDR $end
$var reg 32 ^ GDAT [31:0] $end
$var reg 32 _ GDIR [31:0] $end
$var reg 32 ` GIEN [31:0] $end
$var reg 32 a GIRQ [31:0] $end
$var reg 32 b gpio_in_prev [31:0] $end
$var reg 1 & irq $end
$var reg 32 c prdata [31:0] $end
$var reg 1 # pslverr $end
$upscope $end
$scope task apb_read $end
$var reg 32 d addr [31:0] $end
$upscope $end
$scope task apb_write $end
$var reg 32 e addr [31:0] $end
$var reg 32 f data [31:0] $end
$upscope $end
$upscope $end
$enddefinitions $end
$comment Show the parameter values. $end
$dumpall
b10000011001100 ]
b10000011001000 \
b10000011000000 [
b10000011000100 Z
b10000011000000 Y
b11111 Q
b11110 P
b11101 O
b11100 N
b11011 M
b11010 L
b11001 K
b11000 J
b10111 I
b10110 H
b10101 G
b10100 F
b10011 E
b10010 D
b10001 C
b10000 B
b1111 A
b1110 @
b1101 ?
b1100 >
b1011 =
b1010 <
b1001 ;
b1000 :
b111 9
b110 8
b101 7
b100 6
b11 5
b10 4
b1 3
b0 2
$end
#0
$dumpvars
bx f
bx e
bx d
b0 c
bx b
bx a
bx `
bx _
bx ^
b0 X
b0 W
bx V
bx U
bx T
bx S
bx R
01
00
b0 /
0.
0-
b0 ,
b0 +
b0 *
0)
bx (
bx '
x&
b0 %
0$
x#
bx "
bx !
$end
#10000
bz !
bz T
bz "
b0 R
0#
b0 `
b0 '
b0 V
b0 ^
b0 (
b0 U
b0 _
0&
b0 b
b0 a
1)
#20000
0)
#30000
1)
#40000
0)
b11111111111111111111111111111111 f
b10000011000000 e
11
#50000
bz b
1)
#51000
b11111111111111111111111111111111 /
b11111111111111111111111111111111 X
b10000011000000 ,
b10000011000000 W
10
1.
#60000
0)
#70000
1)
#71000
1$
1-
#80000
0)
#90000
b0 !
b0 T
b0 "
b11111111111111111111111111111111 (
b11111111111111111111111111111111 U
b11111111111111111111111111111111 _
1)
#91000
0$
b10100101101001011010010110100101 f
b10000011000100 e
00
0-
0.
#100000
0)
#110000
b0 S
b0 b
1)
#111000
b10100101101001011010010110100101 /
b10100101101001011010010110100101 X
b10000011000100 ,
b10000011000100 W
10
1.
#120000
0)
#130000
1)
#131000
1$
1-
#140000
0)
#150000
b10100101101001011010010110100101 S
b10100101101001011010010110100101 !
b10100101101001011010010110100101 T
b10100101101001011010010110100101 "
b10100101101001011010010110100101 '
b10100101101001011010010110100101 V
b10100101101001011010010110100101 ^
1)
#151000
0$
00
0-
0.
#160000
0)
#170000
b0 S
b10100101101001011010010110100101 b
1)
#171000
b0 f
b10000011000000 e
#180000
0)
#190000
1)
#191000
b0 /
b0 X
b10000011000000 ,
b10000011000000 W
10
1.
#200000
0)
#210000
1)
#211000
1$
1-
#220000
0)
#230000
bx S
bz !
bz T
bz "
b0 (
b0 U
b0 _
1)
#231000
b10011001100110011001100110011001 S
b111100001111000011110000111100 !
b111100001111000011110000111100 T
b111100001111000011110000111100 "
0$
b111100001111000011110000111100 *
b11111111111111111111111111111111 +
00
0-
0.
#240000
0)
#250000
b0 S
b111100001111000011110000111100 b
1)
#251000
b10000011000100 d
#260000
0)
#270000
1)
#271000
b10000011000100 ,
b10000011000100 W
1.
#280000
0)
#290000
1)
#291000
1$
b111100001111000011110000111100 %
b111100001111000011110000111100 c
1-
#300000
0)
#310000
1)
#311000
0$
b0 %
b0 c
b11111111111111110000000000000000 f
0-
0.
#320000
0)
#330000
1)
#331000
b11111111111111110000000000000000 /
b11111111111111110000000000000000 X
b10000011000000 ,
b10000011000000 W
10
1.
#340000
0)
#350000
1)
#351000
1$
1-
#360000
0)
#370000
bx00xx00xx00xx00x0000000000000000 S
bx01xx10xx01xx10x0011110000111100 !
bx01xx10xx01xx10x0011110000111100 T
bx01xx10xx01xx10x0011110000111100 "
b11111111111111110000000000000000 (
b11111111111111110000000000000000 U
b11111111111111110000000000000000 _
1)
#371000
b10011001100110010110100101101001 S
b10100101101001010101010101010101 !
b10100101101001010101010101010101 T
b10100101101001010101010101010101 "
0$
b10101010101010100000000000000000 f
b10000011000100 e
b101010101010101 *
b1111111111111111 +
00
0-
0.
#380000
0)
#390000
b0 S
b10100101101001010101010101010101 b
1)
#391000
b10101010101010100000000000000000 /
b10101010101010100000000000000000 X
b10000011000100 ,
b10000011000100 W
10
1.
#400000
0)
#410000
1)
#411000
1$
1-
#420000
0)
#430000
b1111000011110000000000000000 S
b10101010101010100101010101010101 !
b10101010101010100101010101010101 T
b10101010101010100101010101010101 "
b10101010101010100000000000000000 '
b10101010101010100000000000000000 V
b10101010101010100000000000000000 ^
1)
#431000
0$
00
0-
0.
#440000
0)
#450000
b0 S
b10101010101010100101010101010101 b
1)
#460000
0)
#470000
1)
#471000
1.
#480000
0)
#490000
1)
#491000
1$
b10101010101010100101010101010101 %
b10101010101010100101010101010101 c
1-
#500000
0)
#510000
1)
#511000
0$
b0 %
b0 c
b11011110101011011011111011101111 f
b10000011000000 e
0-
0.
#520000
0)
#530000
1)
#531000
b11011110101011011011111011101111 /
b11011110101011011011111011101111 X
b10000011000000 ,
b10000011000000 W
10
1.
#540000
0)
#550000
1)
#551000
1$
1-
#560000
0)
#570000
b0x0000x0x0x00x0000x0x000x000x0x S
b10z0101z1z1z10z0010x0x010x010x0x !
b10z0101z1z1z10z0010x0x010x010x0x T
b10z0101z1z1z10z0010x0x010x010x0x "
b11011110101011011011111011101111 (
b11011110101011011011111011101111 U
b11011110101011011011111011101111 _
1)
#571000
0$
b10000011000000 d
00
0-
0.
#580000
0)
#590000
b10z0101z1z1z10z0010x0x010x010x0x b
1)
#591000
1.
#600000
0)
#610000
1)
#611000
1$
b11011110101011011011111011101111 %
b11011110101011011011111011101111 c
1-
#620000
0)
#630000
1)
#631000
0$
b0 %
b0 c
b11111111111111111111111111111111 f
0-
0.
#640000
0)
#650000
1)
#651000
b11111111111111111111111111111111 /
b11111111111111111111111111111111 X
10
1.
#660000
0)
#670000
1)
#671000
1$
1-
#680000
0)
#690000
b0x0000x0x0x00x00x0x0x0x0x0x0x0x S
b10101010101010100x0x0x0x0x0x0x0x !
b10101010101010100x0x0x0x0x0x0x0x T
b10101010101010100x0x0x0x0x0x0x0x "
b11111111111111111111111111111111 (
b11111111111111111111111111111111 U
b11111111111111111111111111111111 _
1)
#691000
bx0x0x0xxxxxxx0x0010x0x010x010x0x S
bx0x0x0x0x0x0x0x00000000000000000 !
bx0x0x0x0x0x0x0x00000000000000000 T
bx0x0x0x0x0x0x0x00000000000000000 "
0$
b0 *
b11111111111111111111111111111111 +
00
0-
0.
#700000
0)
#710000
bx0x0x0x0x0x0x0x00000000000000000 S
bx0x0x0x0x0x0x0x00000000000000000 b
1)
#711000
b10101010101010100000000000000000 !
b10101010101010100000000000000000 T
b10101010101010100000000000000000 "
b10010001101000101011001111000 f
b10000011010000 e
b0 +
#720000
0)
#730000
b0 S
b10101010101010100000000000000000 b
1)
#731000
b10010001101000101011001111000 /
b10010001101000101011001111000 X
b10000011010000 ,
b10000011010000 W
10
1.
#740000
0)
#750000
1)
#751000
1$
1-
#760000
0)
#770000
1#
1)
#771000
0$
00
0-
0.
#780000
0)
#790000
1)
#791000
b0 f
b10000011000000 e
#800000
0)
#810000
1)
#811000
b0 /
b0 X
b10000011000000 ,
b10000011000000 W
10
1.
#820000
0)
#830000
1)
#831000
1$
1-
#840000
0)
#850000
bx S
bz !
bz T
bz "
b0 (
b0 U
b0 _
0#
1)
#851000
0$
b1 f
b10000011001000 e
00
0-
0.
#860000
0)
#870000
bz b
1)
#871000
b1 /
b1 X
b10000011001000 ,
b10000011001000 W
10
1.
#880000
0)
#890000
1)
#891000
1$
1-
#900000
0)
#910000
b0x R
b1 `
1)
#911000
bz0 !
bz0 T
bz0 "
0$
b1 +
00
0-
0.
#920000
0)
#930000
b0 R
bx0 S
b0x a
x&
bz0 b
1)
#931000
b1 R
bx1 S
bz1 !
bz1 T
bz1 "
b1 *
#940000
0)
#950000
b0 R
bx0 S
b1 a
1&
bz1 b
1)
#960000
0)
#970000
0&
1)
#972000
b10000011001100 d
#980000
0)
#990000
1)
#991000
b10000011001100 ,
b10000011001100 W
1.
#1000000
0)
#1010000
1)
#1011000
1$
b1 %
b1 c
1-
#1020000
0)
#1030000
b0 %
b0 c
b0 a
1)
#1031000
0$
0-
0.
#1040000
0)
#1050000
1)
#1051000
b11111111 f
#1060000
0)
#1070000
1)
#1071000
b11111111 /
b11111111 X
b10000011001000 ,
b10000011001000 W
10
1.
#1080000
0)
#1090000
1)
#1091000
1$
1-
#1100000
0)
#1110000
b0xxxxxxx0 R
b11111111 `
1)
#1111000
b0xxxxxxx1 R
bx1 S
bz00000000 !
bz00000000 T
bz00000000 "
0$
b0 *
b11111111 +
00
0-
0.
#1120000
0)
#1130000
b0 R
bx00000000 S
b0xxxxxxx1 a
1&
bz00000000 b
1)
#1131000
b10100101 R
bx10100101 S
bz10100101 !
bz10100101 T
bz10100101 "
b10100101 *
#1140000
0)
#1150000
b0 R
bx00000000 S
b1x1xx1x1 a
bz10100101 b
1)
#1160000
0)
#1170000
0&
1)
#1171000
b10000011001100 ,
b10000011001100 W
1.
#1180000
0)
#1190000
1)
#1191000
1$
b1x1xx1x1 %
b1x1xx1x1 c
1-
#1200000
0)
#1210000
b0 %
b0 c
b0 a
1)
#1211000
0$
0-
0.
#1220000
0)
#1230000
1)
#1232000
b11111111111111111111111111111111 f
b10000011000000 e
#1240000
0)
#1250000
1)
#1251000
b11111111111111111111111111111111 /
b11111111111111111111111111111111 X
b10000011000000 ,
b10000011000000 W
10
1.
#1260000
0)
#1270000
1)
#1271000
1$
1-
#1280000
0)
#1290000
bx0x00x0x S
b101010101010101000000000x0x00x0x !
b101010101010101000000000x0x00x0x T
b101010101010101000000000x0x00x0x "
b11111111111111111111111111111111 (
b11111111111111111111111111111111 U
b11111111111111111111111111111111 _
1)
#1291000
0$
b10000011001000 e
00
0-
0.
#1300000
0)
#1310000
b0x0x00x0x S
b101010101010101000000000x0x00x0x b
1)
#1311000
b10000011001000 ,
b10000011001000 W
10
1.
#1320000
0)
#1330000
1)
#1331000
1$
1-
#1340000
0)
#1350000
b11111111111111111111111111111111 `
1)
#1351000
0$
b0 f
b10000011000100 e
00
0-
0.
#1360000
0)
#1370000
1)
#1371000
b0 /
b0 X
b10000011000100 ,
b10000011000100 W
10
1.
#1380000
0)
#1390000
1)
#1391000
1$
1-
#1400000
0)
#1410000
b101010101010101000000000x0x00x0x S
b0x0x00x0x !
b0x0x00x0x T
b0x0x00x0x "
b0 '
b0 V
b0 ^
1)
#1411000
0$
00
0-
0.
#1420000
0)
#1430000
b0x0x00x0x S
b0x0x00x0x b
1)
#1431000
b11111111111111111111111111111111 f
#1440000
0)
#1450000
1)
#1451000
b11111111111111111111111111111111 /
b11111111111111111111111111111111 X
10
1.
#1460000
0)
#1470000
1)
#1471000
1$
1-
#1480000
0)
#1490000
b111111111111111111111111xxxxxxxx S
b1111111111111111111111111x1xx1x1 !
b1111111111111111111111111x1xx1x1 T
b1111111111111111111111111x1xx1x1 "
b11111111111111111111111111111111 '
b11111111111111111111111111111111 V
b11111111111111111111111111111111 ^
1)
#1491000
0$
00
0-
0.
#1500000
0)
#1510000
b0x0xx0x0 S
b1111111111111111111111111x1xx1x1 b
1)
#1520000
0)
#1530000
1)
#1540000
0)
#1550000
1)
#1551000
b10000011001100 ,
b10000011001100 W
1.
#1560000
0)
#1570000
1)
#1571000
1$
1-
#1580000
0)
#1590000
1)
#1591000
0$
0-
0.
