Verilog/peripherals/timer.v

// hardware timer peripheral for RISC-V SoC
// 2 16-bit timers with interrupt generation
// timers can also generate PWM signals, one PWM per timer
// Registers:
// TCCR - Timer Control Register 0 + 1
// TCCR bit fields: [31:16] TCCR1, [15:0] TCCR0
// TCCR0 -> [15:3] - reserved, [2] - Interrupt Enable, [1] - PWM Enable, [0] - Timer Enable
// TCNT - Timer Counter Register 0 + 1
// TCNT bit fields: [31:16] TCNT1, [15:0] TCNT0 => (0-65535)
// OCMR - Output Compare Register 0 + 1 (for PWM generation)
// OCMR bit fields: [31:16] OCMR1, [15:0] OCMR0 => (0-65535) compare value for PWM duty cycle
// feel free to add more registers for auto-reload, prescaler, etc. if needed (i am lazy)

module timer #(
    parameter BASE_ADDR = 32'h0000_2080,
    parameter BASE_FREQ = 32'h12C00000 // 3250000000 // 50 MHz
) (
    input  wire        clk,
    input  wire        resetn,

    // APB Interface
    input  wire        pclk,
    input  wire        presetn,
    input  wire        psel,
    input  wire        penable,
    input  wire        pwrite,
    input  wire [31:0] paddr,
    input  wire [31:0] pwdata,
    output reg  [31:0] prdata,
    output reg         pready,
    output reg         pslverr,

    // Interrupt
    output reg         irq, // (only for timer 0)
    output reg         pwm_out0,
    output reg         pwm_out1

);


reg [31:0] TCCR; // addr BASE + 0x00
reg [31:0] TCNT; // addr BASE + 0x04
reg [31:0] OCMR; // addr BASE + 0x08
reg [15:0] counter0, counter1; // internal counters

always @(posedge clk) begin // apb write transaction
    if (!resetn) begin
        TCCR <= 32'b0; OCMR <= 32'b0; pslverr <= 1'b0;
    end else if (psel && penable && pwrite) begin
        case (paddr)
            32'h0000_2080: TCCR <= pwdata;
            32'h0000_2088: OCMR <= pwdata;
            default: pslverr <= 1'b1;
        endcase
    end
end

always @(*) begin // apb read transaction
    if (psel && penable && !pwrite) begin
        case (paddr) // read
            32'h0000_2080: prdata = TCCR;
            32'h0000_2084: prdata = TCNT;
            32'h0000_2088: prdata = OCMR;
            default:       prdata = 32'b0;
        endcase
    end else begin
        prdata = 32'b0;
    end
end

assign pready = (psel && penable) ? 1'b1 : 1'b0; // assert only in APB access phase

// timer counting logic
always @(posedge clk) begin
    if (!resetn) begin
        counter0 <= 16'b0; irq <= 1'b0; pwm_out0 <= 1'b0;
    end else if (TCCR[0]) begin // timer enabled
        counter0 <= counter0 + 1; irq <= 1'b0;
        if (counter0 >= OCMR[15:0]) begin
            counter0 <= 16'b0;
            if (TCCR[1]) begin // PWM enabled
                pwm_out0 <= ~pwm_out0; // toggle PWM output on compare match
            end
            if (TCCR[2]) begin // interrupt enabled and compare match
                irq <= 1'b1; // raise interrupt, no interrupt on overflow
            end
        end
    end else begin
        counter0 <= 16'b0; irq <= 1'b0; pwm_out0 <= 1'b0; // reset counter and clear interrupt when timer disabled
    end
end

// timer 1 counting logic (same as timer 0 but no interrupt)
always @(posedge clk) begin
    if (!resetn) begin
        counter1 <= 16'b0; pwm_out1 <= 1'b0;
    end else if (TCCR[16]) begin // timer 1 enabled
        counter1 <= counter1 + 1;
        if (counter1 >= OCMR[31:16]) begin
            counter1 <= 16'b0; // reset counter on compare match, no interrupt
            if (TCCR[17]) begin // PWM enabled
                pwm_out1 <= ~pwm_out1; // toggle PWM output on compare match
            end
        end
    end else begin
        counter1 <= 16'b0; pwm_out1 <= 1'b0; // reset counter and PWM output when timer disabled
    end
end

assign TCNT = {counter1, counter0};

endmodule

Verilog/test/tb_timer.v
`timescale 1ns / 1ps
// testbench to verify the functionality of the timer module
module tb_timer;

reg clk, resetn;
reg psel, penable, pwrite;
reg [31:0] paddr;
reg [31:0] pwdata;
wire [31:0] prdata;
wire pready, pslverr;
wire irq, pwm_out0, pwm_out1;

timer dut (
    .clk(clk),
    .resetn(resetn),
    .pclk(clk),
    .presetn(resetn),
    .psel(psel),
    .penable(penable),
    .pwrite(pwrite),
    .paddr(paddr),
    .pwdata(pwdata),
    .prdata(prdata),
    .pready(pready),
    .pslverr(pslverr),
    .irq(irq),
    .pwm_out0(pwm_out0),
    .pwm_out1(pwm_out1)
);


task apb_write(input [31:0] addr, input [31:0] data);
    begin
        @(posedge clk); #1;
        psel=1; pwrite=1; penable=0; paddr=addr; pwdata=data;
        @(posedge clk); #1;
        penable=1;
        @(posedge clk); #1;
        psel=0; penable=0;
    end
endtask

task apb_read(input [31:0] addr);
    begin
        @(posedge clk); #1;
        psel=1; pwrite=0; penable=0; paddr=addr;
        @(posedge clk); #1;
        penable=1;
        @(posedge clk);
        $display("APB READ [%h] = %h", addr, prdata); #1;
        psel=0; penable=0;
    end
endtask

always #10 clk = ~clk; // 50MHz clock

initial begin
    $dumpfile("./Verilog/dumps/tb_timer.vcd");
    $dumpvars(0, tb_timer);
    // Initialize signals
    clk = 0; resetn = 0; psel = 0; penable = 0; pwrite = 0; paddr = 0; pwdata = 0;
    #100; // Wait for reset to propagate

    resetn = 1; // Release reset

    // Simulate some APB transactions
    apb_write(32'h0000_2088, 32'h0000_00FF); // Set OCMR to 255 BEFORE enabling (else irq fires immediately at OCMR=0)
    apb_write(32'h0000_2080, 32'h0000_0007); // Enable timer (timer en + PWM en + irq en)
    #1000; // Let the timer run

    apb_read(32'h0000_2084); // Read TCNT
    wait (irq); // Wait for interrupt
    $display("time: %0t Timer interrupt triggered!", $time);
    @(posedge clk); #1;
    wait (irq); // Wait for interrupt
    $display("time: %0t Timer interrupt triggered!", $time);
    @(posedge clk); #1;
    wait (irq); // Wait for interrupt
    $display("time: %0t Timer interrupt triggered!", $time);

    apb_write(32'h0000_2088, 32'h0FFF_00FF);
    apb_write(32'h0000_2080, 32'h0001_0007);

    #2000;
    $finish;
end

initial begin // testbench timeout
    #20000;
    $display("Testbench timeout. Something might be wrong.");
    $finish;
end

endmodule

Verilog/dumps/tb_timer.vcd
$date
	Sun Apr  5 01:55:25 2026
$end
$version
	Icarus Verilog
$end
$timescale
	1ps
$end
$scope module tb_timer $end
$var wire 1 ! pwm_out1 $end
$var wire 1 " pwm_out0 $end
$var wire 1 # pslverr $end
$var wire 1 $ pready $end
$var wire 32 % prdata [31:0] $end
$var wire 1 & irq $end
$var reg 1 ' clk $end
$var reg 32 ( paddr [31:0] $end
$var reg 1 ) penable $end
$var reg 1 * psel $end
$var reg 32 + pwdata [31:0] $end
$var reg 1 , pwrite $end
$var reg 1 - resetn $end
$scope module dut $end
$var wire 1 ' clk $end
$var wire 32 . paddr [31:0] $end
$var wire 1 ' pclk $end
$var wire 1 ) penable $end
$var wire 1 - presetn $end
$var wire 1 * psel $end
$var wire 32 / pwdata [31:0] $end
$var wire 1 , pwrite $end
$var wire 1 - resetn $end
$var wire 1 $ pready $end
$var wire 32 0 TCNT [31:0] $end
$var parameter 32 1 BASE_ADDR $end
$var parameter 32 2 BASE_FREQ $end
$var reg 32 3 OCMR [31:0] $end
$var reg 32 4 TCCR [31:0] $end
$var reg 16 5 counter0 [15:0] $end
$var reg 16 6 counter1 [15:0] $end
$var reg 1 & irq $end
$var reg 32 7 prdata [31:0] $end
$var reg 1 # pslverr $end
$var reg 1 " pwm_out0 $end
$var reg 1 ! pwm_out1 $end
$upscope $end
$scope task apb_read $end
$var reg 32 8 addr [31:0] $end
$upscope $end
$scope task apb_write $end
$var reg 32 9 addr [31:0] $end
$var reg 32 : data [31:0] $end
$upscope $end
$upscope $end
$enddefinitions $end
$comment Show the parameter values. $end
$dumpall
b10010110000000000000000000000 2
b10000010000000 1
$end
#0
$dumpvars
bx :
bx 9
bx 8
b0 7
bx 6
bx 5
bx 4
bx 3
bx 0
b0 /
b0 .
0-
0,
b0 +
0*
0)
b0 (
0'
x&
b0 %
0$
x#
x"
x!
$end
#10000
0#
b0 3
b0 4
0"
0&
b0 5
0!
b0 0
b0 6
1'
#20000
0'
#30000
1'
#40000
0'
#50000
1'
#60000
0'
#70000
1'
#80000
0'
#90000
1'
#100000
0'
b11111111 :
b10000010001000 9
1-
#110000
1'
#111000
b11111111 +
b11111111 /
b10000010001000 (
b10000010001000 .
1,
1*
#120000
0'
#130000
1'
#131000
1$
1)
#140000
0'
#150000
b11111111 3
1'
#151000
0$
b111 :
b10000010000000 9
0)
0*
#160000
0'
#170000
1'
#171000
b111 +
b111 /
b10000010000000 (
b10000010000000 .
1*
#180000
0'
#190000
1'
#191000
1$
1)
#200000
0'
#210000
b111 4
1'
#211000
0$
0)
0*
#220000
0'
#230000
b1 0
b1 5
1'
#240000
0'
#250000
b10 0
b10 5
1'
#260000
0'
#270000
b11 0
b11 5
1'
#280000
0'
#290000
b100 0
b100 5
1'
#300000
0'
#310000
b101 0
b101 5
1'
#320000
0'
#330000
b110 0
b110 5
1'
#340000
0'
#350000
b111 0
b111 5
1'
#360000
0'
#370000
b1000 0
b1000 5
1'
#380000
0'
#390000
b1001 0
b1001 5
1'
#400000
0'
#410000
b1010 0
b1010 5
1'
#420000
0'
#430000
b1011 0
b1011 5
1'
#440000
0'
#450000
b1100 0
b1100 5
1'
#460000
0'
#470000
b1101 0
b1101 5
1'
#480000
0'
#490000
b1110 0
b1110 5
1'
#500000
0'
#510000
b1111 0
b1111 5
1'
#520000
0'
#530000
b10000 0
b10000 5
1'
#540000
0'
#550000
b10001 0
b10001 5
1'
#560000
0'
#570000
b10010 0
b10010 5
1'
#580000
0'
#590000
b10011 0
b10011 5
1'
#600000
0'
#610000
b10100 0
b10100 5
1'
#620000
0'
#630000
b10101 0
b10101 5
1'
#640000
0'
#650000
b10110 0
b10110 5
1'
#660000
0'
#670000
b10111 0
b10111 5
1'
#680000
0'
#690000
b11000 0
b11000 5
1'
#700000
0'
#710000
b11001 0
b11001 5
1'
#720000
0'
#730000
b11010 0
b11010 5
1'
#740000
0'
#750000
b11011 0
b11011 5
1'
#760000
0'
#770000
b11100 0
b11100 5
1'
#780000
0'
#790000
b11101 0
b11101 5
1'
#800000
0'
#810000
b11110 0
b11110 5
1'
#820000
0'
#830000
b11111 0
b11111 5
1'
#840000
0'
#850000
b100000 0
b100000 5
1'
#860000
0'
#870000
b100001 0
b100001 5
1'
#880000
0'
#890000
b100010 0
b100010 5
1'
#900000
0'
#910000
b100011 0
b100011 5
1'
#920000
0'
#930000
b100100 0
b100100 5
1'
#940000
0'
#950000
b100101 0
b100101 5
1'
#960000
0'
#970000
b100110 0
b100110 5
1'
#980000
0'
#990000
b100111 0
b100111 5
1'
#1000000
0'
#1010000
b101000 0
b101000 5
1'
#1020000
0'
#1030000
b101001 0
b101001 5
1'
#1040000
0'
#1050000
b101010 0
b101010 5
1'
#1060000
0'
#1070000
b101011 0
b101011 5
1'
#1080000
0'
#1090000
b101100 0
b101100 5
1'
#1100000
0'
#1110000
b101101 0
b101101 5
1'
#1120000
0'
#1130000
b101110 0
b101110 5
1'
#1140000
0'
#1150000
b101111 0
b101111 5
1'
#1160000
0'
#1170000
b110000 0
b110000 5
1'
#1180000
0'
#1190000
b110001 0
b110001 5
1'
#1200000
0'
#1210000
b110010 0
b110010 5
1'
#1211000
b10000010000100 8
#1220000
0'
#1230000
b110011 0
b110011 5
1'
#1231000
b10000010000100 (
b10000010000100 .
0,
1*
#1240000
0'
#1250000
b110100 0
b110100 5
1'
#1251000
1$
b110100 %
b110100 7
1)
#1260000
0'
#1270000
b110101 %
b110101 7
b110101 0
b110101 5
1'
#1271000
0$
b0 %
b0 7
0)
0*
#1280000
0'
#1290000
b110110 0
b110110 5
1'
#1300000
0'
#1310000
b110111 0
b110111 5
1'
#1320000
0'
#1330000
b111000 0
b111000 5
1'
#1340000
0'
#1350000
b111001 0
b111001 5
1'
#1360000
0'
#1370000
b111010 0
b111010 5
1'
#1380000
0'
#1390000
b111011 0
b111011 5
1'
#1400000
0'
#1410000
b111100 0
b111100 5
1'
#1420000
0'
#1430000
b111101 0
b111101 5
1'
#1440000
0'
#1450000
b111110 0
b111110 5
1'
#1460000
0'
#1470000
b111111 0
b111111 5
1'
#1480000
0'
#1490000
b1000000 0
b1000000 5
1'
#1500000
0'
#1510000
b1000001 0
b1000001 5
1'
#1520000
0'
#1530000
b1000010 0
b1000010 5
1'
#1540000
0'
#1550000
b1000011 0
b1000011 5
1'
#1560000
0'
#1570000
b1000100 0
b1000100 5
1'
#1580000
0'
#1590000
b1000101 0
b1000101 5
1'
#1600000
0'
#1610000
b1000110 0
b1000110 5
1'
#1620000
0'
#1630000
b1000111 0
b1000111 5
1'
#1640000
0'
#1650000
b1001000 0
b1001000 5
1'
#1660000
0'
#1670000
b1001001 0
b1001001 5
1'
#1680000
0'
#1690000
b1001010 0
b1001010 5
1'
#1700000
0'
#1710000
b1001011 0
b1001011 5
1'
#1720000
0'
#1730000
b1001100 0
b1001100 5
1'
#1740000
0'
#1750000
b1001101 0
b1001101 5
1'
#1760000
0'
#1770000
b1001110 0
b1001110 5
1'
#1780000
0'
#1790000
b1001111 0
b1001111 5
1'
#1800000
0'
#1810000
b1010000 0
b1010000 5
1'
#1820000
0'
#1830000
b1010001 0
b1010001 5
1'
#1840000
0'
#1850000
b1010010 0
b1010010 5
1'
#1860000
0'
#1870000
b1010011 0
b1010011 5
1'
#1880000
0'
#1890000
b1010100 0
b1010100 5
1'
#1900000
0'
#1910000
b1010101 0
b1010101 5
1'
#1920000
0'
#1930000
b1010110 0
b1010110 5
1'
#1940000
0'
#1950000
b1010111 0
b1010111 5
1'
#1960000
0'
#1970000
b1011000 0
b1011000 5
1'
#1980000
0'
#1990000
b1011001 0
b1011001 5
1'
#2000000
0'
#2010000
b1011010 0
b1011010 5
1'
#2020000
0'
#2030000
b1011011 0
b1011011 5
1'
#2040000
0'
#2050000
b1011100 0
b1011100 5
1'
#2060000
0'
#2070000
b1011101 0
b1011101 5
1'
#2080000
0'
#2090000
b1011110 0
b1011110 5
1'
#2100000
0'
#2110000
b1011111 0
b1011111 5
1'
#2120000
0'
#2130000
b1100000 0
b1100000 5
1'
#2140000
0'
#2150000
b1100001 0
b1100001 5
1'
#2160000
0'
#2170000
b1100010 0
b1100010 5
1'
#2180000
0'
#2190000
b1100011 0
b1100011 5
1'
#2200000
0'
#2210000
b1100100 0
b1100100 5
1'
#2220000
0'
#2230000
b1100101 0
b1100101 5
1'
#2240000
0'
#2250000
b1100110 0
b1100110 5
1'
#2260000
0'
#2270000
b1100111 0
b1100111 5
1'
#2280000
0'
#2290000
b1101000 0
b1101000 5
1'
#2300000
0'
#2310000
b1101001 0
b1101001 5
1'
#2320000
0'
#2330000
b1101010 0
b1101010 5
1'
#2340000
0'
#2350000
b1101011 0
b1101011 5
1'
#2360000
0'
#2370000
b1101100 0
b1101100 5
1'
#2380000
0'
#2390000
b1101101 0
b1101101 5
1'
#2400000
0'
#2410000
b1101110 0
b1101110 5
1'
#2420000
0'
#2430000
b1101111 0
b1101111 5
1'
#2440000
0'
#2450000
b1110000 0
b1110000 5
1'
#2460000
0'
#2470000
b1110001 0
b1110001 5
1'
#2480000
0'
#2490000
b1110010 0
b1110010 5
1'
#2500000
0'
#2510000
b1110011 0
b1110011 5
1'
#2520000
0'
#2530000
b1110100 0
b1110100 5
1'
#2540000
0'
#2550000
b1110101 0
b1110101 5
1'
#2560000
0'
#2570000
b1110110 0
b1110110 5
1'
#2580000
0'
#2590000
b1110111 0
b1110111 5
1'
#2600000
0'
#2610000
b1111000 0
b1111000 5
1'
#2620000
0'
#2630000
b1111001 0
b1111001 5
1'
#2640000
0'
#2650000
b1111010 0
b1111010 5
1'
#2660000
0'
#2670000
b1111011 0
b1111011 5
1'
#2680000
0'
#2690000
b1111100 0
b1111100 5
1'
#2700000
0'
#2710000
b1111101 0
b1111101 5
1'
#2720000
0'
#2730000
b1111110 0
b1111110 5
1'
#2740000
0'
#2750000
b1111111 0
b1111111 5
1'
#2760000
0'
#2770000
b10000000 0
b10000000 5
1'
#2780000
0'
#2790000
b10000001 0
b10000001 5
1'
#2800000
0'
#2810000
b10000010 0
b10000010 5
1'
#2820000
0'
#2830000
b10000011 0
b10000011 5
1'
#2840000
0'
#2850000
b10000100 0
b10000100 5
1'
#2860000
0'
#2870000
b10000101 0
b10000101 5
1'
#2880000
0'
#2890000
b10000110 0
b10000110 5
1'
#2900000
0'
#2910000
b10000111 0
b10000111 5
1'
#2920000
0'
#2930000
b10001000 0
b10001000 5
1'
#2940000
0'
#2950000
b10001001 0
b10001001 5
1'
#2960000
0'
#2970000
b10001010 0
b10001010 5
1'
#2980000
0'
#2990000
b10001011 0
b10001011 5
1'
#3000000
0'
#3010000
b10001100 0
b10001100 5
1'
#3020000
0'
#3030000
b10001101 0
b10001101 5
1'
#3040000
0'
#3050000
b10001110 0
b10001110 5
1'
#3060000
0'
#3070000
b10001111 0
b10001111 5
1'
#3080000
0'
#3090000
b10010000 0
b10010000 5
1'
#3100000
0'
#3110000
b10010001 0
b10010001 5
1'
#3120000
0'
#3130000
b10010010 0
b10010010 5
1'
#3140000
0'
#3150000
b10010011 0
b10010011 5
1'
#3160000
0'
#3170000
b10010100 0
b10010100 5
1'
#3180000
0'
#3190000
b10010101 0
b10010101 5
1'
#3200000
0'
#3210000
b10010110 0
b10010110 5
1'
#3220000
0'
#3230000
b10010111 0
b10010111 5
1'
#3240000
0'
#3250000
b10011000 0
b10011000 5
1'
#3260000
0'
#3270000
b10011001 0
b10011001 5
1'
#3280000
0'
#3290000
b10011010 0
b10011010 5
1'
#3300000
0'
#3310000
b10011011 0
b10011011 5
1'
#3320000
0'
#3330000
b10011100 0
b10011100 5
1'
#3340000
0'
#3350000
b10011101 0
b10011101 5
1'
#3360000
0'
#3370000
b10011110 0
b10011110 5
1'
#3380000
0'
#3390000
b10011111 0
b10011111 5
1'
#3400000
0'
#3410000
b10100000 0
b10100000 5
1'
#3420000
0'
#3430000
b10100001 0
b10100001 5
1'
#3440000
0'
#3450000
b10100010 0
b10100010 5
1'
#3460000
0'
#3470000
b10100011 0
b10100011 5
1'
#3480000
0'
#3490000
b10100100 0
b10100100 5
1'
#3500000
0'
#3510000
b10100101 0
b10100101 5
1'
#3520000
0'
#3530000
b10100110 0
b10100110 5
1'
#3540000
0'
#3550000
b10100111 0
b10100111 5
1'
#3560000
0'
#3570000
b10101000 0
b10101000 5
1'
#3580000
0'
#3590000
b10101001 0
b10101001 5
1'
#3600000
0'
#3610000
b10101010 0
b10101010 5
1'
#3620000
0'
#3630000
b10101011 0
b10101011 5
1'
#3640000
0'
#3650000
b10101100 0
b10101100 5
1'
#3660000
0'
#3670000
b10101101 0
b10101101 5
1'
#3680000
0'
#3690000
b10101110 0
b10101110 5
1'
#3700000
0'
#3710000
b10101111 0
b10101111 5
1'
#3720000
0'
#3730000
b10110000 0
b10110000 5
1'
#3740000
0'
#3750000
b10110001 0
b10110001 5
1'
#3760000
0'
#3770000
b10110010 0
b10110010 5
1'
#3780000
0'
#3790000
b10110011 0
b10110011 5
1'
#3800000
0'
#3810000
b10110100 0
b10110100 5
1'
#3820000
0'
#3830000
b10110101 0
b10110101 5
1'
#3840000
0'
#3850000
b10110110 0
b10110110 5
1'
#3860000
0'
#3870000
b10110111 0
b10110111 5
1'
#3880000
0'
#3890000
b10111000 0
b10111000 5
1'
#3900000
0'
#3910000
b10111001 0
b10111001 5
1'
#3920000
0'
#3930000
b10111010 0
b10111010 5
1'
#3940000
0'
#3950000
b10111011 0
b10111011 5
1'
#3960000
0'
#3970000
b10111100 0
b10111100 5
1'
#3980000
0'
#3990000
b10111101 0
b10111101 5
1'
#4000000
0'
#4010000
b10111110 0
b10111110 5
1'
#4020000
0'
#4030000
b10111111 0
b10111111 5
1'
#4040000
0'
#4050000
b11000000 0
b11000000 5
1'
#4060000
0'
#4070000
b11000001 0
b11000001 5
1'
#4080000
0'
#4090000
b11000010 0
b11000010 5
1'
#4100000
0'
#4110000
b11000011 0
b11000011 5
1'
#4120000
0'
#4130000
b11000100 0
b11000100 5
1'
#4140000
0'
#4150000
b11000101 0
b11000101 5
1'
#4160000
0'
#4170000
b11000110 0
b11000110 5
1'
#4180000
0'
#4190000
b11000111 0
b11000111 5
1'
#4200000
0'
#4210000
b11001000 0
b11001000 5
1'
#4220000
0'
#4230000
b11001001 0
b11001001 5
1'
#4240000
0'
#4250000
b11001010 0
b11001010 5
1'
#4260000
0'
#4270000
b11001011 0
b11001011 5
1'
#4280000
0'
#4290000
b11001100 0
b11001100 5
1'
#4300000
0'
#4310000
b11001101 0
b11001101 5
1'
#4320000
0'
#4330000
b11001110 0
b11001110 5
1'
#4340000
0'
#4350000
b11001111 0
b11001111 5
1'
#4360000
0'
#4370000
b11010000 0
b11010000 5
1'
#4380000
0'
#4390000
b11010001 0
b11010001 5
1'
#4400000
0'
#4410000
b11010010 0
b11010010 5
1'
#4420000
0'
#4430000
b11010011 0
b11010011 5
1'
#4440000
0'
#4450000
b11010100 0
b11010100 5
1'
#4460000
0'
#4470000
b11010101 0
b11010101 5
1'
#4480000
0'
#4490000
b11010110 0
b11010110 5
1'
#4500000
0'
#4510000
b11010111 0
b11010111 5
1'
#4520000
0'
#4530000
b11011000 0
b11011000 5
1'
#4540000
0'
#4550000
b11011001 0
b11011001 5
1'
#4560000
0'
#4570000
b11011010 0
b11011010 5
1'
#4580000
0'
#4590000
b11011011 0
b11011011 5
1'
#4600000
0'
#4610000
b11011100 0
b11011100 5
1'
#4620000
0'
#4630000
b11011101 0
b11011101 5
1'
#4640000
0'
#4650000
b11011110 0
b11011110 5
1'
#4660000
0'
#4670000
b11011111 0
b11011111 5
1'
#4680000
0'
#4690000
b11100000 0
b11100000 5
1'
#4700000
0'
#4710000
b11100001 0
b11100001 5
1'
#4720000
0'
#4730000
b11100010 0
b11100010 5
1'
#4740000
0'
#4750000
b11100011 0
b11100011 5
1'
#4760000
0'
#4770000
b11100100 0
b11100100 5
1'
#4780000
0'
#4790000
b11100101 0
b11100101 5
1'
#4800000
0'
#4810000
b11100110 0
b11100110 5
1'
#4820000
0'
#4830000
b11100111 0
b11100111 5
1'
#4840000
0'
#4850000
b11101000 0
b11101000 5
1'
#4860000
0'
#4870000
b11101001 0
b11101001 5
1'
#4880000
0'
#4890000
b11101010 0
b11101010 5
1'
#4900000
0'
#4910000
b11101011 0
b11101011 5
1'
#4920000
0'
#4930000
b11101100 0
b11101100 5
1'
#4940000
0'
#4950000
b11101101 0
b11101101 5
1'
#4960000
0'
#4970000
b11101110 0
b11101110 5
1'
#4980000
0'
#4990000
b11101111 0
b11101111 5
1'
#5000000
0'
#5010000
b11110000 0
b11110000 5
1'
#5020000
0'
#5030000
b11110001 0
b11110001 5
1'
#5040000
0'
#5050000
b11110010 0
b11110010 5
1'
#5060000
0'
#5070000
b11110011 0
b11110011 5
1'
#5080000
0'
#5090000
b11110100 0
b11110100 5
1'
#5100000
0'
#5110000
b11110101 0
b11110101 5
1'
#5120000
0'
#5130000
b11110110 0
b11110110 5
1'
#5140000
0'
#5150000
b11110111 0
b11110111 5
1'
#5160000
0'
#5170000
b11111000 0
b11111000 5
1'
#5180000
0'
#5190000
b11111001 0
b11111001 5
1'
#5200000
0'
#5210000
b11111010 0
b11111010 5
1'
#5220000
0'
#5230000
b11111011 0
b11111011 5
1'
#5240000
0'
#5250000
b11111100 0
b11111100 5
1'
#5260000
0'
#5270000
b11111101 0
b11111101 5
1'
#5280000
0'
#5290000
b11111110 0
b11111110 5
1'
#5300000
0'
#5310000
b11111111 0
b11111111 5
1'
#5320000
0'
#5330000
1&
1"
b0 0
b0 5
1'
#5340000
0'
#5350000
0&
b1 0
b1 5
1'
#5360000
0'
#5370000
b10 0
b10 5
1'
#5380000
0'
#5390000
b11 0
b11 5
1'
#5400000
0'
#5410000
b100 0
b100 5
1'
#5420000
0'
#5430000
b101 0
b101 5
1'
#5440000
0'
#5450000
b110 0
b110 5
1'
#5460000
0'
#5470000
b111 0
b111 5
1'
#5480000
0'
#5490000
b1000 0
b1000 5
1'
#5500000
0'
#5510000
b1001 0
b1001 5
1'
#5520000
0'
#5530000
b1010 0
b1010 5
1'
#5540000
0'
#5550000
b1011 0
b1011 5
1'
#5560000
0'
#5570000
b1100 0
b1100 5
1'
#5580000
0'
#5590000
b1101 0
b1101 5
1'
#5600000
0'
#5610000
b1110 0
b1110 5
1'
#5620000
0'
#5630000
b1111 0
b1111 5
1'
#5640000
0'
#5650000
b10000 0
b10000 5
1'
#5660000
0'
#5670000
b10001 0
b10001 5
1'
#5680000
0'
#5690000
b10010 0
b10010 5
1'
#5700000
0'
#5710000
b10011 0
b10011 5
1'
#5720000
0'
#5730000
b10100 0
b10100 5
1'
#5740000
0'
#5750000
b10101 0
b10101 5
1'
#5760000
0'
#5770000
b10110 0
b10110 5
1'
#5780000
0'
#5790000
b10111 0
b10111 5
1'
#5800000
0'
#5810000
b11000 0
b11000 5
1'
#5820000
0'
#5830000
b11001 0
b11001 5
1'
#5840000
0'
#5850000
b11010 0
b11010 5
1'
#5860000
0'
#5870000
b11011 0
b11011 5
1'
#5880000
0'
#5890000
b11100 0
b11100 5
1'
#5900000
0'
#5910000
b11101 0
b11101 5
1'
#5920000
0'
#5930000
b11110 0
b11110 5
1'
#5940000
0'
#5950000
b11111 0
b11111 5
1'
#5960000
0'
#5970000
b100000 0
b100000 5
1'
#5980000
0'
#5990000
b100001 0
b100001 5
1'
#6000000
0'
#6010000
b100010 0
b100010 5
1'
#6020000
0'
#6030000
b100011 0
b100011 5
1'
#6040000
0'
#6050000
b100100 0
b100100 5
1'
#6060000
0'
#6070000
b100101 0
b100101 5
1'
#6080000
0'
#6090000
b100110 0
b100110 5
1'
#6100000
0'
#6110000
b100111 0
b100111 5
1'
#6120000
0'
#6130000
b101000 0
b101000 5
1'
#6140000
0'
#6150000
b101001 0
b101001 5
1'
#6160000
0'
#6170000
b101010 0
b101010 5
1'
#6180000
0'
#6190000
b101011 0
b101011 5
1'
#6200000
0'
#6210000
b101100 0
b101100 5
1'
#6220000
0'
#6230000
b101101 0
b101101 5
1'
#6240000
0'
#6250000
b101110 0
b101110 5
1'
#6260000
0'
#6270000
b101111 0
b101111 5
1'
#6280000
0'
#6290000
b110000 0
b110000 5
1'
#6300000
0'
#6310000
b110001 0
b110001 5
1'
#6320000
0'
#6330000
b110010 0
b110010 5
1'
#6340000
0'
#6350000
b110011 0
b110011 5
1'
#6360000
0'
#6370000
b110100 0
b110100 5
1'
#6380000
0'
#6390000
b110101 0
b110101 5
1'
#6400000
0'
#6410000
b110110 0
b110110 5
1'
#6420000
0'
#6430000
b110111 0
b110111 5
1'
#6440000
0'
#6450000
b111000 0
b111000 5
1'
#6460000
0'
#6470000
b111001 0
b111001 5
1'
#6480000
0'
#6490000
b111010 0
b111010 5
1'
#6500000
0'
#6510000
b111011 0
b111011 5
1'
#6520000
0'
#6530000
b111100 0
b111100 5
1'
#6540000
0'
#6550000
b111101 0
b111101 5
1'
#6560000
0'
#6570000
b111110 0
b111110 5
1'
#6580000
0'
#6590000
b111111 0
b111111 5
1'
#6600000
0'
#6610000
b1000000 0
b1000000 5
1'
#6620000
0'
#6630000
b1000001 0
b1000001 5
1'
#6640000
0'
#6650000
b1000010 0
b1000010 5
1'
#6660000
0'
#6670000
b1000011 0
b1000011 5
1'
#6680000
0'
#6690000
b1000100 0
b1000100 5
1'
#6700000
0'
#6710000
b1000101 0
b1000101 5
1'
#6720000
0'
#6730000
b1000110 0
b1000110 5
1'
#6740000
0'
#6750000
b1000111 0
b1000111 5
1'
#6760000
0'
#6770000
b1001000 0
b1001000 5
1'
#6780000
0'
#6790000
b1001001 0
b1001001 5
1'
#6800000
0'
#6810000
b1001010 0
b1001010 5
1'
#6820000
0'
#6830000
b1001011 0
b1001011 5
1'
#6840000
0'
#6850000
b1001100 0
b1001100 5
1'
#6860000
0'
#6870000
b1001101 0
b1001101 5
1'
#6880000
0'
#6890000
b1001110 0
b1001110 5
1'
#6900000
0'
#6910000
b1001111 0
b1001111 5
1'
#6920000
0'
#6930000
b1010000 0
b1010000 5
1'
#6940000
0'
#6950000
b1010001 0
b1010001 5
1'
#6960000
0'
#6970000
b1010010 0
b1010010 5
1'
#6980000
0'
#6990000
b1010011 0
b1010011 5
1'
#7000000
0'
#7010000
b1010100 0
b1010100 5
1'
#7020000
0'
#7030000
b1010101 0
b1010101 5
1'
#7040000
0'
#7050000
b1010110 0
b1010110 5
1'
#7060000
0'
#7070000
b1010111 0
b1010111 5
1'
#7080000
0'
#7090000
b1011000 0
b1011000 5
1'
#7100000
0'
#7110000
b1011001 0
b1011001 5
1'
#7120000
0'
#7130000
b1011010 0
b1011010 5
1'
#7140000
0'
#7150000
b1011011 0
b1011011 5
1'
#7160000
0'
#7170000
b1011100 0
b1011100 5
1'
#7180000
0'
#7190000
b1011101 0
b1011101 5
1'
#7200000
0'
#7210000
b1011110 0
b1011110 5
1'
#7220000
0'
#7230000
b1011111 0
b1011111 5
1'
#7240000
0'
#7250000
b1100000 0
b1100000 5
1'
#7260000
0'
#7270000
b1100001 0
b1100001 5
1'
#7280000
0'
#7290000
b1100010 0
b1100010 5
1'
#7300000
0'
#7310000
b1100011 0
b1100011 5
1'
#7320000
0'
#7330000
b1100100 0
b1100100 5
1'
#7340000
0'
#7350000
b1100101 0
b1100101 5
1'
#7360000
0'
#7370000
b1100110 0
b1100110 5
1'
#7380000
0'
#7390000
b1100111 0
b1100111 5
1'
#7400000
0'
#7410000
b1101000 0
b1101000 5
1'
#7420000
0'
#7430000
b1101001 0
b1101001 5
1'
#7440000
0'
#7450000
b1101010 0
b1101010 5
1'
#7460000
0'
#7470000
b1101011 0
b1101011 5
1'
#7480000
0'
#7490000
b1101100 0
b1101100 5
1'
#7500000
0'
#7510000
b1101101 0
b1101101 5
1'
#7520000
0'
#7530000
b1101110 0
b1101110 5
1'
#7540000
0'
#7550000
b1101111 0
b1101111 5
1'
#7560000
0'
